<?xml version="1.0" encoding="utf-8"?><Dokument edixistatus=""><MetaMeeting><ParliamentarySession>20142</ParliamentarySession><ParliamentaryGroup>Folketinget</ParliamentaryGroup><MeetingNumber>5</MeetingNumber><DateOfSitting>2015-08-21T10:00:00</DateOfSitting><Location>Folketingssalen</Location><EdixiDocLocation>W:\20142\M005\</EdixiDocLocation><AudioFileFolder>X:\Arbor\FT20142\005\SALEN\</AudioFileFolder></MetaMeeting><TitelGruppe><Titel><Linea><Char>5. møde</Char></Linea></Titel><UnderTitel><Linea><Char>Fredag den 21. august 2015 kl. 10.00</Char></Linea></UnderTitel></TitelGruppe><DagsordenPlan><Rubrica>
  <Linea>
    <Char>Dagsorden</Char>
  </Linea>
</Rubrica>
<PunktTekst>
  <Exitus>
    <Linea>
      <Char>1) 2. behandling af lovforslag nr. L 3:</Char>
    </Linea>
  </Exitus>
  <Exitus>
    <Linea>
      <Char>Forslag til lov om ændring af lov om social pension.
(Harmonisering af regler om opgørelse af bopælstid for folkepension).</Char>
    </Linea>
  </Exitus>
  <Exitus>
    <Linea>
      <Char>Af beskæftigelsesministeren (Jørn Neergaard Larsen).</Char>
    </Linea>
  </Exitus>
  <Exitus>
    <Linea>
      <Char>(Fremsættelse 03.07.2015. 1. behandling 03.07.2015. Betænkning 19.08.2015).</Char>
    </Linea>
  </Exitus>
</PunktTekst>
<PunktTekst>
  <Exitus>
    <Linea>
      <Char>2) 2. behandling af lovforslag nr. L 4:</Char>
    </Linea>
  </Exitus>
  <Exitus>
    <Linea>
      <Char>Forslag til lov om kommunernes finansiering af visse offentlige ydelser udbetalt af kommunerne, Udbetaling Danmark og arbejdsløshedskasserne.</Char>
    </Linea>
  </Exitus>
  <Exitus>
    <Linea>
      <Char>Af beskæftigelsesministeren (Jørn Neergaard Larsen).</Char>
    </Linea>
  </Exitus>
  <Exitus>
    <Linea>
      <Char>(Fremsættelse 03.07.2015. 1. behandling 03.07.2015. Betænkning 19.08.2015).</Char>
    </Linea>
  </Exitus>
</PunktTekst>
<PunktTekst>
  <Exitus>
    <Linea>
      <Char>3) 2. behandling af lovforslag nr. L 1:</Char>
    </Linea>
  </Exitus>
  <Exitus>
    <Linea>
      <Char>Forslag til lov om ændring af lov om kommunal udligning og
generelle tilskud til kommuner.
(Tilpasninger i udligningssystemet som følge af omlægning af refusionssystemet på beskæftigelsesområdet).</Char>
    </Linea>
  </Exitus>
  <Exitus>
    <Linea>
      <Char>Af social- og indenrigsministeren (Karen Ellemann).</Char>
    </Linea>
  </Exitus>
  <Exitus>
    <Linea>
      <Char>(Fremsættelse 03.07.2015. 1. behandling 03.07.2015. Betænkning 19.08.2015).</Char>
    </Linea>
  </Exitus>
</PunktTekst>
<PunktTekst>
  <Exitus>
    <Linea>
      <Char>4) 2. behandling af lovforslag nr. L 2:</Char>
    </Linea>
  </Exitus>
  <Exitus>
    <Linea>
      <Char>Forslag til lov om ændring af lov om aktiv socialpolitik, lov om en aktiv beskæftigelsesindsats, integrationsloven og forskellige andre love.
(Indførelse af en integrationsydelse, ændring af reglerne om ret til uddannelses- og kontanthjælp m.v.).</Char>
    </Linea>
  </Exitus>
  <Exitus>
    <Linea>
      <Char>Af udlændinge-, integrations- og boligministeren (Inger Støjberg).</Char>
    </Linea>
  </Exitus>
  <Exitus>
    <Linea>
      <Char>(Fremsættelse 03.07.2015. 1. behandling 03.07.2015. Betænkning 18.08.2015).</Char>
    </Linea>
  </Exitus>
</PunktTekst>
<PunktTekst>
  <Exitus>
    <Linea>
      <Char>5) 2. behandling af lovforslag nr. L 5:</Char>
    </Linea>
  </Exitus>
  <Exitus>
    <Linea>
      <Char>Forslag til lov om ændring af ligningsloven.
(Genindførelse af boligjobordningen).</Char>
    </Linea>
  </Exitus>
  <Exitus>
    <Linea>
      <Char>Af skatteministeren (Karsten Lauritzen).</Char>
    </Linea>
  </Exitus>
  <Exitus>
    <Linea>
      <Char>(Fremsættelse 03.07.2015. 1. behandling 03.07.2015. Betænkning 18.08.2015).</Char>
    </Linea>
  </Exitus>
</PunktTekst>
<PunktTekst>
  <Exitus>
    <Linea>
      <Char>6) 2. behandling af lovforslag nr. L 6:</Char>
    </Linea>
  </Exitus>
  <Exitus>
    <Linea>
      <Char>Forslag til lov om ændring af opkrævningsloven og selskabsskatteloven.
(Ændring af rentetillæg for afregning af selskabsskat og begrænsning af indestående på skattekontoen m.v.).</Char>
    </Linea>
  </Exitus>
  <Exitus>
    <Linea>
      <Char>Af skatteministeren (Karsten Lauritzen).</Char>
    </Linea>
  </Exitus>
  <Exitus>
    <Linea>
      <Char>(Fremsættelse 03.07.2015. 1. behandling 03.07.2015. Betænkning 18.08.2015).</Char>
    </Linea>
  </Exitus>
</PunktTekst>
<PunktTekst>
  <Exitus>
    <Linea>
      <Char>7) 2. behandling af lovforslag nr. L 7:</Char>
    </Linea>
  </Exitus>
  <Exitus>
    <Linea>
      <Char>Forslag til lov om ændring af lov om børnetilskud og forskudsvis udbetaling af børnebidrag og lov om en børne- og ungeydelse. (Genindførelse af optjeningsprincippet for ret til børnetilskud og børne- og ungeydelse for flygtninge).</Char>
    </Linea>
  </Exitus>
  <Exitus>
    <Linea>
      <Char>Af skatteministeren (Karsten Lauritzen).</Char>
    </Linea>
  </Exitus>
  <Exitus>
    <Linea>
      <Char>(Fremsættelse 03.07.2015. 1. behandling 03.07.2015. Betænkning 19.08.2015).</Char>
    </Linea>
  </Exitus>
</PunktTekst>
<PunktTekst>
  <Exitus>
    <Linea>
      <Char>8) 1. behandling af beslutningsforslag nr. B 5:</Char>
    </Linea>
  </Exitus>
  <Exitus>
    <Linea>
      <Char>Forslag til folketingsbeslutning om ændring af forretningsorden for Folketinget. (Nedlæggelse og sammenlægning af visse stående udvalg).</Char>
    </Linea>
  </Exitus>
  <Exitus>
    <Linea>
      <Char>(Forslag som fremsat (i betænkning) 03.07.2015. Anmeldelse (i salen) 03.07.2015).</Char>
    </Linea>
  </Exitus>
</PunktTekst></DagsordenPlan><DagsordenPunkt><MetaFTAgendaItem><ItemNo>0</ItemNo><FTCase /><FTCaseNumber /><FTCaseType>FM</FTCaseType><FTCaseStage /><ShortTitle>Punkt 0</ShortTitle></MetaFTAgendaItem><PunktTekst><Exitus><Linea><Char /></Linea></Exitus></PunktTekst><Aktivitet><Tale><Taler><MetaSpeakerMP><OratorFirstName>Pia</OratorFirstName><OratorLastName>Kjærsgaard</OratorLastName><GroupNameShort>DF</GroupNameShort><OratorRole>formand</OratorRole></MetaSpeakerMP><TalerTitel><Linea><Char>Formanden</Char><Char /></Linea></TalerTitel></Taler><TaleSegment><MetaSpeechSegment><LastModified>2016-02-24T12:25:51</LastModified><EdixiStatus>Typeset</EdixiStatus><StartDateTime>2015-08-21T10:00:20</StartDateTime><EndDateTime>2015-08-21T10:00:34</EndDateTime></MetaSpeechSegment><TekstGruppe><Exitus><Linea><Char>Mødet er åbnet.</Char></Linea></Exitus></TekstGruppe></TaleSegment></Tale></Aktivitet></DagsordenPunkt><DagsordenPunkt><MetaFTAgendaItem><ItemNo>1</ItemNo><FTCase /><FTCaseNumber>3</FTCaseNumber><FTCaseType>L</FTCaseType><FTCaseStage>BEH2</FTCaseStage><ShortTitle>2. behandling af L 3: Om harmonisering af regler om opgørelse af bopælstid for folkepension.</ShortTitle></MetaFTAgendaItem><PunktTekst><PreTekst><Exitus><Linea><Char>Det første punkt på dagsordenen er:</Char></Linea></Exitus></PreTekst><Exitus><Linea><Char>1) 2. behandling af lovforslag nr. L 3:</Char></Linea></Exitus><Exitus><Linea><Char>Forslag til lov om ændring af lov om social pension.
(Harmonisering af regler om opgørelse af bopælstid for folkepension).</Char></Linea></Exitus><Exitus><Linea><Char>Af beskæftigelsesministeren (Jørn Neergaard Larsen).</Char></Linea></Exitus><Exitus><Linea><Char>(Fremsættelse 03.07.2015. 1. behandling 03.07.2015. Betænkning 19.08.2015).</Char></Linea></Exitus></PunktTekst><Aktivitet><Rubrica><Linea><Char>Forhandling</Char></Linea></Rubrica><Tale><Taler><MetaSpeakerMP><OratorFirstName>Pia</OratorFirstName><OratorLastName>Kjærsgaard</OratorLastName><GroupNameShort>DF</GroupNameShort><OratorRole>formand</OratorRole></MetaSpeakerMP><TalerTitel><Linea><Char>Formanden</Char><Char /></Linea></TalerTitel></Taler><TaleSegment><MetaSpeechSegment><LastModified>2016-02-24T12:25:51</LastModified><EdixiStatus>Typeset</EdixiStatus><StartDateTime>2015-08-21T10:00:34</StartDateTime><EndDateTime>2015-08-21T10:01:02</EndDateTime></MetaSpeechSegment><TekstGruppe><Exitus><Linea><Char>Der er ikke stillet ændringsforslag.</Char></Linea></Exitus><Exitus><Linea><Char>Er der nogen, der ønsker at udtale sig?</Char></Linea><Linea><Char>Fru Johanne Schmidt-Nielsen, værsgo.</Char></Linea></Exitus></TekstGruppe></TaleSegment></Tale><Tale><Taler><MetaSpeakerMP><OratorFirstName>Johanne</OratorFirstName><OratorLastName>Schmidt-Nielsen</OratorLastName><GroupNameShort>EL</GroupNameShort><OratorRole>medlem</OratorRole></MetaSpeakerMP><TalerTitel><Linea><Char>Johanne Schmidt-Nielsen</Char><Char> (EL)</Char></Linea></TalerTitel></Taler><TaleType><Linea><Char>Ordfører</Char></Linea></TaleType><TaleSegment><MetaSpeechSegment><LastModified>2016-02-24T12:25:51</LastModified><EdixiStatus>Typeset</EdixiStatus><StartDateTime>2015-08-21T10:01:02</StartDateTime><EndDateTime>2015-08-21T10:06:10</EndDateTime></MetaSpeechSegment><TekstGruppe><Exitus><Linea><Char>Helt overordnet vil jeg sige, at vi jo skal andenbehandle tre lovforslag på flygtningeområdet i dag.</Char></Linea><Linea><Char>Og når jeg tager ordet under andenbehandlingen, skyldes det bl.a., at vi under førstebehandlingen var i den situation, at der ikke var høringssvar, at der ikke var noget høringsnotat, fordi man valgte at haste lovgivningsprocessen igennem.</Char></Linea><Linea><Char>Det må jeg sige:</Char></Linea><Linea><Char>Det synes jeg er dårlig stil.</Char></Linea><Linea><Char>Jeg synes, at man altid som regering må tilstræbe at få så god en lovgivningsproces som overhovedet muligt, herunder at sørge for, at alle de relevante organisationer osv.</Char></Linea><Linea><Char>bliver hørt i tide.</Char></Linea><Linea><Char>Og jeg kan ikke se noget argument for, at det her skulle sjuskes igennem.</Char></Linea></Exitus><Exitus><Linea><Char>Men nu har vi så en andenbehandling, og grundlæggende om de her tre lovforslag vil jeg sige, at vi står i en historisk flygtningekrise.</Char></Linea><Linea><Char>Altså, ikke siden anden verdenskrig har så mange mennesker været tvunget på flugt.</Char></Linea><Linea><Char>Jeg synes faktisk, det er helt vildt, at den måde, Danmark reagerer på det, er ved at spørge:</Char></Linea><Linea><Char>Hvordan kan vi gøre mest muligt for at undgå, at flygtningene kommer hertil?</Char></Linea></Exitus><Exitus><Linea><Char>Det her forslag, L 3, handler jo om at fratage flygtninge retten til folkepension.</Char></Linea><Linea><Char>Det vil sige, at flygtninge, som ikke har boet mange, mange år i Danmark, kommer til at tilbringe de sidste år i fattigdom.</Char></Linea></Exitus><Exitus><Linea><Char>Der er jo to hovedargumenter fra regeringens side for de her tre lovforslag.</Char></Linea><Linea><Char>Det ene er, at det vil få folk hurtigere i arbejde, hvis man gør dem fattigere.</Char></Linea><Linea><Char>Det er jo sådan en argumentation, som højrefløjen dyrker generelt.</Char></Linea><Linea><Char>Jeg mener, at den er tvivlsom, også når det handler om arbejdsløse danskere osv., men nu er det altså flygtninge, vi taler om.</Char></Linea><Linea><Char>Som sagt er argument nr.</Char></Linea><Linea><Char>1 fra regeringens side, at det vil få mennesker hurtigere i arbejde.</Char></Linea><Linea><Char>Og der må man bare sige:</Char></Linea><Linea><Char>Her taler vi om folkepensionister, altså om mennesker, der ikke skal arbejde, fordi de er for gamle til at arbejde.</Char></Linea><Linea><Char>Så den argumentation falder jo fuldstændig på gulvet.</Char></Linea></Exitus><Exitus><Linea><Char>Det andet argument er, at det vil få folk til at blive væk, altså at søge til et andet land end Danmark, hvis man giver lave ydelser.</Char></Linea><Linea><Char>Jeg har ikke på nogen måde kunnet få regeringen til at komme med noget forskningsmæssigt belæg for den påstand og da slet ikke nogen som helst form for dokumentation for sammenhængen mellem pensionens størrelse eller muligheden for at få folkepension og så, hvilket land man vælger.</Char></Linea><Linea><Char>Beskæftigelsesministeren sagde såmænd også på det samråd, vi havde i tirsdags, meget klart:</Char></Linea><Linea><Char>Nej, regeringen og ministeren kan ikke dokumentere det eller har ikke nogen erfaring, der tyder på, at folkepensionens størrelse eller muligheden for at få folkepension har betydning for, hvilket land flygtninge vælger at tage til.</Char></Linea><Linea><Char>UNHCR, altså FN's Flygtningehøjkommissariat, mener jo faktisk, at det her forslag er i strid med flygtningekonventionen.</Char></Linea><Linea><Char>Institut for Menneskerettigheder har også tidligere været ude at sige, at de faktisk mener, at man vedtager lovgivning, som strider mod flygtningekonventionen fra 1951.</Char></Linea><Linea><Char>En lang række organisationer tager også afstand fra det her forslag med den argumentation, at det vil skabe fattigdom.</Char></Linea><Linea><Char>Og fattigdom er sådan cirka det dummeste, man kan skabe, hvis man gerne vil god integration.</Char></Linea></Exitus><Exitus><Linea><Char>En hovedanke fra vores side, fra Enhedslistens side, i forhold til de her tre lovforslag, vi andenbehandler i dag, er jo netop, at man simpelt hen skyder sig selv i foden, at man spænder ben for sig selv, hvis ønsket er god integration.</Char></Linea><Linea><Char>For hvis vi placerer mennesker i fattigdom, isolerer vi dem og skubber dem væk fra samfundet; vi skubber dem længere væk fra arbejdsmarkedet.</Char></Linea><Linea><Char>Og for de mennesker, det her forslag vedrører, er arbejdsmarkedet jo slet ikke en mulighed, fordi det netop vedrører ældre borgere.</Char></Linea></Exitus><Exitus><Linea><Char>Derudover mener jeg, at det her forslag vil komme til at medføre et kæmpemæssigt bureaukrati ude i kommunerne.</Char></Linea><Linea><Char>For det vil, som der skrives i lovforslaget, være sådan, at hvis den enkelte ældre borger er i en situation, hvor man ikke kan betale huslejen eller sidder så stramt i det, at man ikke kan få mad på bordet eller betale sin medicin, eller hvad det nu kunne være, så vil man have mulighed for at søge enkeltstående ydelser.</Char></Linea><Linea><Char>Jeg frygter, at det her kommer til at medføre et meget stort bureaukrati, hvor vores sagsbehandlere rundtomkring i kommunerne skal bruge en masse tid på at sidde og tildele enkeltstående ydelser og forholde sig til den enkeltes økonomi, frem for at vi siger, at de her mennesker selvfølgelig skal have en pension, man kan leve af.</Char></Linea><Linea><Char>Så det vil sige, at jeg sådan set også tvivler på besparelsen i det her.</Char></Linea><Linea><Char>Tværtimod tror jeg, at de bureaukratiske omkostninger, om man så må sige, må blive meget, meget store.</Char></Linea></Exitus><Exitus><Linea><Char>Vi stemmer selvfølgelig imod det her lovforslag.</Char></Linea><Linea><Char>Og som sagt mener jeg simpelt hen ikke, at argumentationen holder.</Char></Linea><Linea><Char>Det giver ikke mening at sige, at man skal motivere mennesker til at arbejde ved at sætte ydelsen ned, når der er tale om ældre mennesker, som netop ikke kan eller skal arbejde.</Char></Linea></Exitus></TekstGruppe></TaleSegment></Tale><Tale><Taler><MetaSpeakerMP><OratorFirstName>Pia</OratorFirstName><OratorLastName>Kjærsgaard</OratorLastName><GroupNameShort>DF</GroupNameShort><OratorRole>formand</OratorRole></MetaSpeakerMP><TalerTitel><Linea><Char>Formanden</Char><Char /></Linea></TalerTitel></Taler><TaleSegment><MetaSpeechSegment><LastModified>2016-02-24T12:25:51</LastModified><EdixiStatus>Typeset</EdixiStatus><StartDateTime>2015-08-21T10:06:10</StartDateTime><EndDateTime>2015-08-21T10:06:31</EndDateTime></MetaSpeechSegment><TekstGruppe><Exitus><Linea><Char>Tak til Enhedslistens ordfører.</Char></Linea><Linea><Char>Er der nogen, der ønsker at udtale sig yderligere?</Char></Linea></Exitus><Exitus><Linea><Char>Det er der ikke.</Char></Linea><Linea><Char>Så er forhandlingen sluttet.</Char></Linea></Exitus></TekstGruppe><TekstGruppe><Exitus><Linea><Char>Jeg foreslår, at lovforslaget går direkte til tredje behandling uden fornyet udvalgsbehandling, og hvis ingen gør indsigelse, betragter jeg dette som vedtaget.</Char></Linea></Exitus><Exitus><Linea><Char>Det er vedtaget.</Char></Linea></Exitus></TekstGruppe></TaleSegment></Tale></Aktivitet></DagsordenPunkt><DagsordenPunkt><MetaFTAgendaItem><ItemNo>2</ItemNo><FTCase /><FTCaseNumber>4</FTCaseNumber><FTCaseType>L</FTCaseType><FTCaseStage>BEH2</FTCaseStage><ShortTitle>2. behandling af L 4: Om kommunernes finansiering af visse offentlige ydelser m.v.</ShortTitle></MetaFTAgendaItem><PunktTekst><PreTekst><Exitus><Linea><Char>Det næste punkt på dagsordenen er:</Char></Linea></Exitus></PreTekst><Exitus><Linea><Char>2) 2. behandling af lovforslag nr. L 4:</Char></Linea></Exitus><Exitus><Linea><Char>Forslag til lov om kommunernes finansiering af visse offentlige ydelser udbetalt af kommunerne, Udbetaling Danmark og arbejdsløshedskasserne.</Char></Linea></Exitus><Exitus><Linea><Char>Af beskæftigelsesministeren (Jørn Neergaard Larsen).</Char></Linea></Exitus><Exitus><Linea><Char>(Fremsættelse 03.07.2015. 1. behandling 03.07.2015. Betænkning 19.08.2015).</Char></Linea></Exitus></PunktTekst><Aktivitet><Rubrica><Linea><Char>Forhandling</Char></Linea></Rubrica><Tale><Taler><MetaSpeakerMP><OratorFirstName>Pia</OratorFirstName><OratorLastName>Kjærsgaard</OratorLastName><GroupNameShort>DF</GroupNameShort><OratorRole>formand</OratorRole></MetaSpeakerMP><TalerTitel><Linea><Char>Formanden</Char><Char /></Linea></TalerTitel></Taler><TaleSegment><MetaSpeechSegment><LastModified>2016-02-24T12:25:51</LastModified><EdixiStatus>Typeset</EdixiStatus><StartDateTime>2015-08-21T10:06:31</StartDateTime><EndDateTime>2015-08-21T10:06:59</EndDateTime></MetaSpeechSegment><TekstGruppe><Exitus><Linea><Char>Er der nogen, der ønsker at udtale sig?</Char></Linea></Exitus><Exitus><Linea><Char>Da det ikke er tilfældet, er forhandlingen sluttet, og vi går til afstemning.</Char></Linea></Exitus></TekstGruppe></TaleSegment></Tale></Aktivitet><Aktivitet><Rubrica><Linea><Char>Afstemning</Char></Linea></Rubrica><Tale><Taler><MetaSpeakerMP><OratorFirstName>Pia</OratorFirstName><OratorLastName>Kjærsgaard</OratorLastName><GroupNameShort>DF</GroupNameShort><OratorRole>formand</OratorRole></MetaSpeakerMP><TalerTitel><Linea><Char>Formanden</Char><Char /></Linea></TalerTitel></Taler><TaleSegment><MetaSpeechSegment><LastModified>2016-02-24T12:25:51</LastModified><EdixiStatus>Typeset</EdixiStatus><StartDateTime>2015-08-21T10:06:59</StartDateTime><EndDateTime>2015-08-21T10:07:18</EndDateTime></MetaSpeechSegment><TekstGruppe><Exitus><Linea><Char>Ønskes afstemning om ændringsforslag nr.</Char></Linea><Linea><Char>1-4, tiltrådt af udvalget?</Char></Linea></Exitus><Exitus><Linea><Char>De er vedtaget.</Char></Linea></Exitus></TekstGruppe><TekstGruppe><Exitus><Linea><Char>Jeg foreslår, at lovforslaget går direkte til tredje behandling uden fornyet udvalgsbehandling, og hvis ingen gør indsigelse, betragter jeg dette som vedtaget.</Char></Linea></Exitus><Exitus><Linea><Char>Det er vedtaget.</Char></Linea></Exitus></TekstGruppe></TaleSegment></Tale></Aktivitet></DagsordenPunkt><DagsordenPunkt><MetaFTAgendaItem><ItemNo>3</ItemNo><FTCase /><FTCaseNumber>1</FTCaseNumber><FTCaseType>L</FTCaseType><FTCaseStage>BEH2</FTCaseStage><ShortTitle>2. behandling af L 1: Om tilpasninger i udligningssystemet som følge af omlægning af refusionssystemet på beskæftigelsesområdet.</ShortTitle></MetaFTAgendaItem><PunktTekst><PreTekst>
  <Exitus>
    <Linea>
      <Char>Det næste punkt på dagsordenen er:</Char>
    </Linea>
  </Exitus>
</PreTekst>
<Exitus>
  <Linea>
    <Char>3) 2. behandling af lovforslag nr. L 1:</Char>
  </Linea>
</Exitus>
<Exitus>
  <Linea>
    <Char>Forslag til lov om ændring af lov om kommunal udligning og
generelle tilskud til kommuner. (Tilpasninger i udligningssystemet som følge af omlægning af refusionssystemet på beskæftigelsesområdet).</Char>
  </Linea>
</Exitus>
<Exitus>
  <Linea>
    <Char>Af social- og indenrigsministeren (Karen Ellemann).</Char>
  </Linea>
</Exitus>
<Exitus>
  <Linea>
    <Char>(Fremsættelse 03.07.2015. 1. behandling 03.07.2015. Betænkning 19.08.2015).</Char>
  </Linea>
</Exitus></PunktTekst><Aktivitet><Rubrica><Linea><Char>Forhandling</Char></Linea></Rubrica><Tale><Taler><MetaSpeakerMP><OratorFirstName>Pia</OratorFirstName><OratorLastName>Kjærsgaard</OratorLastName><GroupNameShort>DF</GroupNameShort><OratorRole>formand</OratorRole></MetaSpeakerMP><TalerTitel><Linea><Char>Formanden</Char><Char /></Linea></TalerTitel></Taler><TaleSegment><MetaSpeechSegment><LastModified>2016-02-24T12:25:51</LastModified><EdixiStatus>Typeset</EdixiStatus><StartDateTime>2015-08-21T10:07:18</StartDateTime><EndDateTime>2015-08-21T10:07:52</EndDateTime></MetaSpeechSegment><TekstGruppe><Exitus><Linea><Char>Der er ikke stillet ændringsforslag.</Char></Linea></Exitus><Exitus><Linea><Char>Er der nogen, der ønsker at udtale sig?</Char></Linea></Exitus><Exitus><Linea><Char>Da det ikke er tilfældet, er forhandlingen sluttet.</Char></Linea></Exitus></TekstGruppe><TekstGruppe><Exitus><Linea><Char>Jeg foreslår, at lovforslaget går direkte til tredje behandling uden fornyet udvalgsbehandling, og hvis ingen gør indsigelse, betragter jeg dette som vedtaget.</Char></Linea></Exitus><Exitus><Linea><Char>Det er vedtaget.</Char></Linea></Exitus></TekstGruppe></TaleSegment></Tale></Aktivitet></DagsordenPunkt><DagsordenPunkt><MetaFTAgendaItem><ItemNo>4</ItemNo><FTCase /><FTCaseNumber>2</FTCaseNumber><FTCaseType>L</FTCaseType><FTCaseStage>BEH2</FTCaseStage><ShortTitle>2. behandling af L 2: Om indførelse af en integrationsydelse, ændring af reglerne om ret til uddannelses- og kontanthjælp.</ShortTitle></MetaFTAgendaItem><PunktTekst><PreTekst><Exitus><Linea><Char>Det næste punkt på dagsordenen er:</Char></Linea></Exitus></PreTekst><Exitus><Linea><Char>4) 2. behandling af lovforslag nr. L 2:</Char></Linea></Exitus><Exitus><Linea><Char>Forslag til lov om ændring af lov om aktiv socialpolitik, lov om en aktiv beskæftigelsesindsats, integrationsloven og forskellige andre love.
(Indførelse af en integrationsydelse, ændring af reglerne om ret til uddannelses- og kontanthjælp m.v.).</Char></Linea></Exitus><Exitus><Linea><Char>Af udlændinge-, integrations- og boligministeren (Inger Støjberg).</Char></Linea></Exitus><Exitus><Linea><Char>(Fremsættelse 03.07.2015. 1. behandling 03.07.2015. Betænkning 18.08.2015).</Char></Linea></Exitus></PunktTekst><Aktivitet><Rubrica><Linea><Char>Forhandling</Char></Linea></Rubrica><Tale><Taler><MetaSpeakerMP><OratorFirstName>Pia</OratorFirstName><OratorLastName>Kjærsgaard</OratorLastName><GroupNameShort>DF</GroupNameShort><OratorRole>formand</OratorRole></MetaSpeakerMP><TalerTitel><Linea><Char>Formanden</Char><Char /></Linea></TalerTitel></Taler><TaleSegment><MetaSpeechSegment><LastModified>2016-02-24T12:25:51</LastModified><EdixiStatus>Typeset</EdixiStatus><StartDateTime>2015-08-21T10:07:52</StartDateTime><EndDateTime>2015-08-21T10:08:14</EndDateTime></MetaSpeechSegment><TekstGruppe><Exitus><Linea><Char>Ønsker nogen at udtale sig?</Char></Linea><Linea><Char>Fru Johanne Schmidt-Nielsen, Enhedslisten, værsgo.</Char></Linea></Exitus></TekstGruppe></TaleSegment></Tale><Tale><Taler><MetaSpeakerMP><OratorFirstName>Johanne</OratorFirstName><OratorLastName>Schmidt-Nielsen</OratorLastName><GroupNameShort>EL</GroupNameShort><OratorRole>medlem</OratorRole></MetaSpeakerMP><TalerTitel><Linea><Char>Johanne Schmidt-Nielsen</Char><Char> (EL)</Char></Linea></TalerTitel></Taler><TaleType><Linea><Char>Ordfører</Char></Linea></TaleType><TaleSegment><MetaSpeechSegment><LastModified>2016-02-24T12:25:51</LastModified><EdixiStatus>Typeset</EdixiStatus><StartDateTime>2015-08-21T10:08:14</StartDateTime><EndDateTime>2015-08-21T10:13:17</EndDateTime></MetaSpeechSegment><TekstGruppe><Exitus><Linea><Char>Tak for det.</Char></Linea><Linea><Char>Det her er jo så det andet forslag i rækken af tre, som handler om at forringe vilkårene for flygtninge her i Danmark.</Char></Linea></Exitus><Exitus><Linea><Char>Igen må jeg helt overordnet sige:</Char></Linea><Linea><Char>Man kan simpelt hen ikke på den ene side sige, at man gerne vil styrke integrationen, og så på den anden side placere mennesker i fattigdom.</Char></Linea><Linea><Char>Det bliver konsekvensen af de lovforslag, vi behandler i dag.</Char></Linea></Exitus><Exitus><Linea><Char>Jeg vil gerne komme med en række bemærkninger.</Char></Linea><Linea><Char>Den første handler om den danskprøvebonus, som regeringen lægger op til.</Char></Linea><Linea><Char>Når den er værd at nævne, er det jo, fordi regeringen, når den er blevet kritiseret for, at de her lovforslag vil føre til fattigdom, har svaret:</Char></Linea><Linea><Char>Jamen folk kan jo bestå en danskprøve, nemlig danskprøve 2, og så få den her bonus.</Char></Linea><Linea><Char>Til det er der jo at sige, at godt en tredjedel – 34-39 pct.</Char></Linea><Linea><Char>– af flygtninge og familiesammenførte, der kommer til Danmark, placeres på det, der hedder danskuddannelse 1.</Char></Linea><Linea><Char>Det er ikke noget, de selv vælger.</Char></Linea><Linea><Char>Altså, det er sådan, at når man kommer til Danmark, bliver man vurderet af sprogcenteret:</Char></Linea><Linea><Char>Hvilket danskuddannelsesniveau har du?</Char></Linea><Linea><Char>Når man så har gennemført danskuddannelsen på det niveau, bestået prøven, har man ikke ret til mere danskundervisning.</Char></Linea><Linea><Char>Så for godt en tredjedel vil det altså ikke være en mulighed at komme op på det niveau, som kræves, for at man kan modtage den her bonus.</Char></Linea></Exitus><Exitus><Linea><Char>Ikke mindst de mennesker, som kommer hertil med andre alfabeter end det latinske, bliver placeret på danskuddannelse 1-niveau.</Char></Linea><Linea><Char>Regeringen henviser til det, der hedder FVU, forberedende voksenundervisning, som et alternativ.</Char></Linea><Linea><Char>Det fremgår af et skriftligt svar, jeg har fået, at når flygtninge så har bestået niveau 1 og ikke har ret til mere sprogundervisning, ikke har ret til en ny prøve, kan de jo komme hen i det her FVU-system.</Char></Linea><Linea><Char>Problemet er bare, at det kræver, at kommunen accepterer og har lyst til at betale for det særlige undervisningsforløb.</Char></Linea><Linea><Char>Og i øvrigt er den her forberedende voksenundervisning slet ikke lavet til flygtninge i den her situation.</Char></Linea><Linea><Char>Med andre ord vil en stor del af de flygtninge, der kommer hertil, reelt være afskåret fra den her bonus.</Char></Linea></Exitus><Exitus><Linea><Char>Det andet, jeg gerne vil sige, er, at flygtninge, som har børn, og som jo er på integrationsydelse i den første tid her i landet, vil have et ekstremt lavt rådighedsbeløb, fordi de ikke får børnetilskud.</Char></Linea><Linea><Char>Rådighedsbeløbet for en enlig med tre børn vil være på 5.300 kr.</Char></Linea><Linea><Char>om måneden og ikke de 14.500 kr., som fremgik af regeringens faktaark – fakta i citationstegn, skulle man sige – fra juli.</Char></Linea><Linea><Char>Der vil i den grad være tale om børn, som kommer til at leve i fattigdom, i modsætning til hvad hr.</Char></Linea><Linea><Char>Lars Løkke Rasmussen, statsministeren, lovede under valgkampen.</Char></Linea></Exitus><Exitus><Linea><Char>Punkt 3:</Char></Linea><Linea><Char>Vi mangler stadig dokumentation for, at asylansøgere vælger land efter niveauet på ydelserne.</Char></Linea><Linea><Char>Enhedslisten har henvist til forskere, som konstaterer, at der ikke er nogen statistisk signifikant sammenhæng mellem valg af land og ydelsesniveau.</Char></Linea><Linea><Char>Jeg har ikke kunnet få regeringen til at tilbagevise den forskning eller pege på en forskning, som tyder på noget andet.</Char></Linea></Exitus><Exitus><Linea><Char>Punkt 4:</Char></Linea><Linea><Char>Den beskæftigelsesmæssige effekt ved starthjælpen var ekstremt begrænset – 14 pct., så vidt jeg husker.</Char></Linea><Linea><Char>Altså, 14 pct.</Char></Linea><Linea><Char>ekstra kom i arbejde, og resten blev bare fattigere.</Char></Linea><Linea><Char>Og når jeg siger »bare«, lyder det sådan lidt ligegyldigt, men det er bestemt ikke ligegyldigt.</Char></Linea><Linea><Char>Det medførte voldsomme, massive sociale problemer.</Char></Linea><Linea><Char>Ud over at det er problem for det enkelte menneske, er det rigtig, rigtig dyrt for det danske samfund at sende mennesker ud i den type fattigdom.</Char></Linea><Linea><Char>Oven i købet er det sådan med det lovforslag, vi behandler i dag, at den her lave ydelse, som altså skal motivere flygtninge til at arbejde, også gælder for de flygtninge, som af danske sagsbehandlere er blevet vurderet til ikke at være i stand til at arbejde – altså de mennesker, som ikke er arbejdsmarkedsparate.</Char></Linea><Linea><Char>Så giver det jo slet ikke mening.</Char></Linea><Linea><Char>På den ene side siger man:</Char></Linea><Linea><Char>Vi laver en lav ydelse, fordi det vil få folk til at komme i arbejde.</Char></Linea><Linea><Char>På den anden side siger man:</Char></Linea><Linea><Char>Men det skal også gælde for de mennesker, som vi selv har vurderet ikke vil være i stand til at arbejde.</Char></Linea><Linea><Char>Igen:</Char></Linea><Linea><Char>Resultatet af det her vil for langt de fleste være fattigdom med dertil hørende massive sociale problemer.</Char></Linea><Linea><Char>Det er ikke kun et problem for den enkelte borger, der udsættes for det her, men i den grad et problem for hele det danske samfund, fordi integrationsproblemer går ud over os alle sammen.</Char></Linea></Exitus><Exitus><Linea><Char>Punkt 5:</Char></Linea><Linea><Char> Den svenske terrorismeekspert Magnus Ranstorp og psykologen David Oehlenschläger fra DIGNITY, Dansk Institut Mod Tortur, frygter, at marginaliserede flygtningebørn, der vokser op i fattigdom, er i fare for radikalisering.</Char></Linea><Linea><Char>Altså, de udtaler direkte, at konsekvensen af det her kan være, at risikoen for radikalisering vokser.</Char></Linea><Linea><Char>Det er igen et kæmpemæssigt problem for det danske samfund.</Char></Linea></Exitus></TekstGruppe></TaleSegment><TaleSegment><MetaSpeechSegment><LastModified>2016-02-24T12:25:51</LastModified><EdixiStatus>Typeset</EdixiStatus><StartDateTime>2015-08-21T10:13:24</StartDateTime><EndDateTime>2015-08-21T10:14:49</EndDateTime></MetaSpeechSegment><TekstGruppe><Exitus><Linea><Char>Punkt 6:</Char></Linea><Linea><Char>Ministeren har flere gange henvist til, at hvis flygtninge virkelig kommer på spanden på grund af den her meget lave ydelse, vil der være mulighed for at få en særlig støtte til høje boligudgifter.</Char></Linea><Linea><Char>Det, ministeren så bare ikke har henvist til i de svar, er, at regeringen har tænkt sig at lægge et loft over den støtte, som kan gives til særlig høje boligudgifter.</Char></Linea></Exitus><Exitus><Linea><Char>Punkt 7:</Char></Linea><Linea><Char>Lovforslaget er blevet mødt med en bred front af kritik for diskrimination, for at skabe fattigdom, for at modvirke integration.</Char></Linea><Linea><Char>Kritikken kommer bl.a.</Char></Linea><Linea><Char>fra Socialrådgiverforeningen, Amnesty International, Institut for Menneskerettigheder, Red Barnet, LO, FTF, Uddannelsesforbundet, Dansk Folkeoplysnings Samråd, Børnerådet, Dansk Flygtningehjælp, De Danske Sprogcentre, Dansk Institut mod Tortur, Røde Kors, Rådet for Socialt Udsatte, AOF Danmark og Retspolitisk Forening.</Char></Linea></Exitus><Exitus><Linea><Char>Hvis man på nogen måde er interesseret i god integration, hvis man synes, det er et problem, når flygtninge havner i kriminalitet, når flygtninge ender med ikke at kunne det danske sprog, når flygtninge ikke kommer ud og bliver en del af det danske samfund, så er det simpelt hen tudetosset at stemme for det her lovforslag, for det her lovforslag vil i den grad øge risikoen for integrationsproblemer frem for at gøre det modsatte.</Char></Linea><Linea><Char>Jeg synes, at det er dybt bekymrende.</Char></Linea></Exitus></TekstGruppe></TaleSegment></Tale><Tale><Taler><MetaSpeakerMP><OratorFirstName>Pia</OratorFirstName><OratorLastName>Kjærsgaard</OratorLastName><GroupNameShort>DF</GroupNameShort><OratorRole>formand</OratorRole></MetaSpeakerMP><TalerTitel><Linea><Char>Formanden</Char><Char /></Linea></TalerTitel></Taler><TaleSegment><MetaSpeechSegment><LastModified>2016-02-24T12:25:51</LastModified><EdixiStatus>Typeset</EdixiStatus><StartDateTime>2015-08-21T10:14:49</StartDateTime><EndDateTime>2015-08-21T10:14:58</EndDateTime></MetaSpeechSegment><TekstGruppe><Exitus><Linea><Char>Tak til fru Johanne Schmidt-Nielsen.</Char></Linea><Linea><Char>Hr.</Char></Linea><Linea><Char>Martin Henriksen for en kort bemærkning – eller er det en ordførertale?</Char></Linea><Linea><Char>Det er for så vidt ligegyldigt.</Char></Linea><Linea><Char>Værsgo.</Char></Linea></Exitus></TekstGruppe></TaleSegment></Tale><Tale><Taler><MetaSpeakerMP><OratorFirstName>Martin</OratorFirstName><OratorLastName>Henriksen</OratorLastName><GroupNameShort>DF</GroupNameShort><OratorRole>medlem</OratorRole></MetaSpeakerMP><TalerTitel><Linea><Char>Martin Henriksen</Char><Char> (DF)</Char></Linea></TalerTitel></Taler><TaleSegment><MetaSpeechSegment><LastModified>2016-02-24T12:25:51</LastModified><EdixiStatus>Typeset</EdixiStatus><StartDateTime>2015-08-21T10:14:58</StartDateTime><EndDateTime>2015-08-21T10:15:34</EndDateTime></MetaSpeechSegment><TekstGruppe><Exitus><Linea><Char>Tak for det.</Char></Linea><Linea><Char>Jeg vil godt spørge Enhedslisten, hvorfor man, når man kommer til Danmark, så skal have stillet alt muligt gratis til rådighed.</Char></Linea><Linea><Char>Altså, hvis man skal op og have en ekstra bonus fra det offentlige, og man skal have sprogundervisning for nu at nå derop til, så skal den absolut være stillet gratis til rådighed.</Char></Linea><Linea><Char>Hvorfor skal det være gratis?</Char></Linea><Linea><Char>Hvorfor er det en naturlov for Enhedslisten, at fordi du kommer til Danmark, og du har fået en opholdstilladelse, fordi der er nogle, der har taget dig så seriøst, at de har kigget på din ansøgning, og du så ender med at blive her, så skal man åbne op for velfærdssamfundet?</Char></Linea><Linea><Char>Hvorfor mener Enhedslisten f.eks.</Char></Linea><Linea><Char>ikke, at man skal gøre sig fortjent til noget, før man kan få det?</Char></Linea><Linea><Char>Er det ikke også sådan for socialister et meget rimeligt synspunkt?</Char></Linea></Exitus></TekstGruppe></TaleSegment></Tale><Tale><Taler><MetaSpeakerMP><OratorFirstName>Pia</OratorFirstName><OratorLastName>Kjærsgaard</OratorLastName><GroupNameShort>DF</GroupNameShort><OratorRole>formand</OratorRole></MetaSpeakerMP><TalerTitel><Linea><Char>Formanden</Char><Char /></Linea></TalerTitel></Taler><TaleSegment><MetaSpeechSegment><LastModified>2016-02-24T12:25:51</LastModified><EdixiStatus>Typeset</EdixiStatus><StartDateTime>2015-08-21T10:15:34</StartDateTime><EndDateTime>2015-08-21T10:15:36</EndDateTime></MetaSpeechSegment><TekstGruppe><Exitus><Linea><Char>Værsgo, ordføreren.</Char></Linea></Exitus></TekstGruppe></TaleSegment></Tale><Tale><Taler><MetaSpeakerMP><OratorFirstName>Johanne</OratorFirstName><OratorLastName>Schmidt-Nielsen</OratorLastName><GroupNameShort>EL</GroupNameShort><OratorRole>medlem</OratorRole></MetaSpeakerMP><TalerTitel><Linea><Char>Johanne Schmidt-Nielsen</Char><Char> (EL)</Char></Linea></TalerTitel></Taler><TaleSegment><MetaSpeechSegment><LastModified>2016-02-24T12:25:51</LastModified><EdixiStatus>Typeset</EdixiStatus><StartDateTime>2015-08-21T10:15:36</StartDateTime><EndDateTime>2015-08-21T10:17:16</EndDateTime></MetaSpeechSegment><TekstGruppe><Exitus><Linea><Char>Hr.</Char></Linea><Linea><Char>Martin Henriksen tager fat i danskundervisning og spørger:</Char></Linea><Linea><Char>Hvorfor skal den være gratis til rådighed?</Char></Linea><Linea><Char>Altså, når der kommer flygtninge hertil, hvorfor skal de så have adgang til danskundervisning?</Char></Linea><Linea><Char>Skal de ikke betale for det?</Char></Linea></Exitus><Exitus><Linea><Char>Hvis man indførte det princip, at vi sagde til de flygtninge, der kommer hertil og var anerkendt som flygtninge, dvs.</Char></Linea><Linea><Char>at de danske myndigheder havde sagt, at du er i fare, dit liv er i fare, vi vil ikke sende dig tilbage, for så risikerer du at blive slået ihjel, derfor har du lovligt ophold i Danmark, du har krav på beskyttelse i Danmark, at de selv skal betale for deres danskundervisning, så ville der som det første ske det, at de færreste ville få danskundervisning.</Char></Linea><Linea><Char>Der er ikke særlig mange flygtninge, som kommer med en masse penge.</Char></Linea><Linea><Char>De fleste har enten mistet alt, hvad de ejer og har, eller har solgt det for at finde en måde at betale for at komme ud af f.eks.</Char></Linea><Linea><Char>Syrien på på flugt fra Islamisk Stats myrderier og voldtægter og tortur.</Char></Linea></Exitus><Exitus><Linea><Char>Ville det gavne det danske samfund, at der var en masse flygtninge i Danmark, som ikke havde adgang til danskundervisning og som dermed ikke lærte det danske sprog?</Char></Linea><Linea><Char>Nej.</Char></Linea><Linea><Char>Det ville da være et kæmpemæssigt problem.</Char></Linea><Linea><Char>Det ville være et kæmpemæssigt problem for os alle sammen.</Char></Linea><Linea><Char>Det ville betyde, at de her menneskers mulighed for at komme på arbejdsmarkedet og blive selvforsørgende ville blive endnu ringere, end den er i dag.</Char></Linea><Linea><Char>Det er ikke let at komme hertil i forvejen og komme ud på det danske arbejdsmarked.</Char></Linea></Exitus><Exitus><Linea><Char>Så jeg tror, at det sådan cirka er det dummeste, man kunne finde på at gøre, hvis man ønsker integration, altså at fratage flygtningene retten til danskundervisning.</Char></Linea><Linea><Char>Så vidt jeg husker, havde Dansk Folkeparti på et tidspunkt et forslag eller måske bare en overvejelse om, at mennesker fra andre lande kun måtte tale dansk på gaden.</Char></Linea><Linea><Char>Mange flygtninge ville i så fald skulle være tavse, når de gik rundt på de danske gader.</Char></Linea></Exitus></TekstGruppe></TaleSegment></Tale><Tale><Taler><MetaSpeakerMP><OratorFirstName>Pia</OratorFirstName><OratorLastName>Kjærsgaard</OratorLastName><GroupNameShort>DF</GroupNameShort><OratorRole>formand</OratorRole></MetaSpeakerMP><TalerTitel><Linea><Char>Formanden</Char><Char /></Linea></TalerTitel></Taler><TaleSegment><MetaSpeechSegment><LastModified>2016-02-24T12:25:51</LastModified><EdixiStatus>Typeset</EdixiStatus><StartDateTime>2015-08-21T10:17:16</StartDateTime><EndDateTime>2015-08-21T10:17:18</EndDateTime></MetaSpeechSegment><TekstGruppe><Exitus><Linea><Char>Vi skal lige overholde taletiden.</Char></Linea></Exitus><Exitus><Linea><Char>Værsgo, hr.</Char></Linea><Linea><Char>Martin Henriksen.</Char></Linea></Exitus></TekstGruppe></TaleSegment></Tale><Tale><Taler><MetaSpeakerMP><OratorFirstName>Martin</OratorFirstName><OratorLastName>Henriksen</OratorLastName><GroupNameShort>DF</GroupNameShort><OratorRole>medlem</OratorRole></MetaSpeakerMP><TalerTitel><Linea><Char>Martin Henriksen</Char><Char> (DF)</Char></Linea></TalerTitel></Taler><TaleSegment><MetaSpeechSegment><LastModified>2016-02-24T12:25:51</LastModified><EdixiStatus>Typeset</EdixiStatus><StartDateTime>2015-08-21T10:17:18</StartDateTime><EndDateTime>2015-08-21T10:18:05</EndDateTime></MetaSpeechSegment><TekstGruppe><Exitus><Linea><Char>Det var en fin tale.</Char></Linea><Linea><Char>Jamen jeg vil bare lige slå fast:</Char></Linea><Linea><Char>Flygtninge har jo stadig væk ret til gratis danskundervisning.</Char></Linea><Linea><Char>Det bliver der jo sådan set ikke ændret ved med det her lovforslag.</Char></Linea><Linea><Char>Fru Johanne Schmidt-Nielsen vil så have endnu mere gratis danskundervisning.</Char></Linea><Linea><Char>Det er jo det, der er spørgsmålet, og der siger vi så, at de jo får noget i forvejen.</Char></Linea><Linea><Char>Der er ingen grund til, at man bliver ved med at gøre flere ting gratis i det danske samfund.</Char></Linea></Exitus><Exitus><Linea><Char>Men jeg fik i øvrigt ikke svar på det spørgsmål, som jeg stillede:</Char></Linea><Linea><Char>Hvorfor synes Enhedslisten, at det er urimeligt, at man siger, at folk, der kommer til Danmark, f.eks.</Char></Linea><Linea><Char>skal arbejde i en årrække eller være her en årrække for at optjene ret til alle de andre ting, som folk, hvis familier har været her gennem generationer, har?</Char></Linea><Linea><Char>Hvorfor er det urimeligt?</Char></Linea><Linea><Char>Jeg forstår det simpelt hen ikke.</Char></Linea><Linea><Char>Det er da et meget godt princip, og så lærer vi også de her mennesker, hvis de ender med at blive her – vi vil gerne sende dem tilbage, men hvis de ender med at blive her – at man faktisk skal gøre sig umage for at få noget ud af sin tilværelse i Danmark.</Char></Linea></Exitus></TekstGruppe></TaleSegment></Tale><Tale><Taler><MetaSpeakerMP><OratorFirstName>Pia</OratorFirstName><OratorLastName>Kjærsgaard</OratorLastName><GroupNameShort>DF</GroupNameShort><OratorRole>formand</OratorRole></MetaSpeakerMP><TalerTitel><Linea><Char>Formanden</Char><Char /></Linea></TalerTitel></Taler><TaleSegment><MetaSpeechSegment><LastModified>2016-02-24T12:25:51</LastModified><EdixiStatus>Typeset</EdixiStatus><StartDateTime>2015-08-21T10:18:05</StartDateTime><EndDateTime>2015-08-21T10:18:06</EndDateTime></MetaSpeechSegment><TekstGruppe><Exitus><Linea><Char>Tak.</Char></Linea><Linea><Char>Ordføreren.</Char></Linea></Exitus></TekstGruppe></TaleSegment></Tale><Tale><Taler><MetaSpeakerMP><OratorFirstName>Johanne</OratorFirstName><OratorLastName>Schmidt-Nielsen</OratorLastName><GroupNameShort>EL</GroupNameShort><OratorRole>medlem</OratorRole></MetaSpeakerMP><TalerTitel><Linea><Char>Johanne Schmidt-Nielsen</Char><Char> (EL)</Char></Linea></TalerTitel></Taler><TaleSegment><MetaSpeechSegment><LastModified>2016-02-24T12:25:51</LastModified><EdixiStatus>Typeset</EdixiStatus><StartDateTime>2015-08-21T10:18:06</StartDateTime><EndDateTime>2015-08-21T10:19:07</EndDateTime></MetaSpeechSegment><TekstGruppe><Exitus><Linea><Char>Da flygtningekonventionen blev lavet i 1951, var der en række lande i verden, der gik sammen og sagde:</Char></Linea><Linea><Char>Den måde, som flygtningene i forbindelse med anden verdenskrig blev behandlet på, var utilgivelig, det kunne man ikke acceptere.</Char></Linea><Linea><Char>Man blev nødt til at lave fælles regler for at beskytte mennesker på flugt.</Char></Linea></Exitus><Exitus><Linea><Char>Vi har set, at det ikke altid er sådan, at den stat, som et menneske bor i, behandler et menneske godt.</Char></Linea><Linea><Char>Vi så desværre også, hvordan en række lande afviste de flygtninge, der kom fra Tyskland, med de voldsomme konsekvenser, som det nu engang havde til følge.</Char></Linea><Linea><Char>Derfor lavede man en flygtningekonvention og sagde, at hvis mennesker er på flugt, skal vi sørge for at behandle dem ordentligt.</Char></Linea><Linea><Char>Det er ikke et frit valg fra deres side, at de har været tvunget på flugt.</Char></Linea></Exitus><Exitus><Linea><Char>Så jeg støtter i allerhøjeste grad, at vi tager vores ansvar på os i forhold til at beskytte mennesker på flugt.</Char></Linea><Linea><Char>Ikke mindst af hensyn til det danske samfund er det så fornuftigt, at vi tager integrationsopgaven alvorligt, herunder den opgave, det er at sørge for, at de lærer dansk.</Char></Linea></Exitus></TekstGruppe></TaleSegment></Tale><Tale><Taler><MetaSpeakerMP><OratorFirstName>Pia</OratorFirstName><OratorLastName>Kjærsgaard</OratorLastName><GroupNameShort>DF</GroupNameShort><OratorRole>formand</OratorRole></MetaSpeakerMP><TalerTitel><Linea><Char>Formanden</Char><Char /></Linea></TalerTitel></Taler><TaleSegment><MetaSpeechSegment><LastModified>2016-02-24T12:25:51</LastModified><EdixiStatus>Typeset</EdixiStatus><StartDateTime>2015-08-21T10:19:07</StartDateTime><EndDateTime>2015-08-21T10:19:29</EndDateTime></MetaSpeechSegment><TekstGruppe><Exitus><Linea><Char>Tak til ordføreren.</Char></Linea><Linea><Char>Der er ikke flere korte bemærkninger, så vi går til ordførerrækken.</Char></Linea><Linea><Char>Den første er fru Ulla Sandbæk, Alternativet, værsgo.</Char></Linea></Exitus></TekstGruppe></TaleSegment></Tale><Tale><Taler><MetaSpeakerMP><OratorFirstName>Ulla</OratorFirstName><OratorLastName>Sandbæk</OratorLastName><GroupNameShort>ALT</GroupNameShort><OratorRole>medlem</OratorRole></MetaSpeakerMP><TalerTitel><Linea><Char>Ulla Sandbæk</Char><Char> (ALT)</Char></Linea></TalerTitel></Taler><TaleType><Linea><Char>Ordfører</Char></Linea></TaleType><TaleSegment><MetaSpeechSegment><LastModified>2016-02-24T12:25:51</LastModified><EdixiStatus>Typeset</EdixiStatus><StartDateTime>2015-08-21T10:19:29</StartDateTime><EndDateTime>2015-08-21T10:23:03</EndDateTime></MetaSpeechSegment><TekstGruppe><Exitus><Linea><Char>Tak, fru formand.</Char></Linea><Linea><Char>Jeg har været præst i 35 år, og derfor er jeg jo faktisk tvunget til at tro på mirakler, og det er derfor, jeg tager ordet i dag.</Char></Linea></Exitus><Exitus><Linea><Char>Der er også en anden grund til det.</Char></Linea><Linea><Char>Ved førstebehandlingen havde vi jo endnu ikke fået nogen høringssvar.</Char></Linea><Linea><Char>Det har vi så fået her ved andenbehandlingen.</Char></Linea><Linea><Char>De høringssvar sætter alle sammen et meget stort spørgsmålstegn ved hele det fundament, som dette lovforslag hviler på, nemlig at hvis man laver en meget lav integrationsydelse, så kommer folk ud på arbejdsmarkedet.</Char></Linea><Linea><Char>Jeg havde jo gerne set, at regeringens dokumentation af, at folk rent faktisk kommer ud på arbejdsmarkedet, ville være lige så grundig som den dokumentation eller i hvert fald de antagelser, vi ser i høringssvarene, om, at den lave integrationsydelse ikke vil få folk ud på arbejdsmarkedet.</Char></Linea><Linea><Char>Jeg har stort set kun hørt den dokumentation fra regeringen, at det tror regeringen ikke på.</Char></Linea><Linea><Char>Regeringen er uenig i alt det, som høringssvarene siger.</Char></Linea><Linea><Char>Regeringen siger, at folk kommer nødvendigvis ud på det danske arbejdsmarked i det øjeblik, man sætter integrationsydelsen ned.</Char></Linea></Exitus><Exitus><Linea><Char>Nu går regeringen vel ikke ud fra, at det er hundrede procent af flygtningene, som kommer ud på arbejdsmarkedet, så der vil i hvert fald være en hel del mennesker, som vil komme ud for det, som alle høringssvarene påpeger, og som jeg også påpegede i førstebehandlingen, men som høringssvarene nu underbygger, nemlig det, at det vil blive meget svært med integrationen af flygtninge, hvis de altså ikke kommer ud på arbejdsmarkedet, hvad man ikke må gå ud fra at hundrede procent af flygtningene gør.</Char></Linea><Linea><Char>Der vil blive lavet ghettodannelser, fordi flygtningene kun vil kunne bo ganske bestemte steder med den meget lave ydelse.</Char></Linea><Linea><Char>Flygtningene vil ikke kunne komme til danskundervisning.</Char></Linea><Linea><Char>De vil simpelt hen ikke få råd til at betale en busbillet.</Char></Linea><Linea><Char>De vil skulle bruge al deres tid på at finde den billigste mad.</Char></Linea><Linea><Char>Ikke engang mad i supermarkeder, som er meget billige, vil de kunne købe for de penge, de får, og det vil især gå ud over deres børn.</Char></Linea><Linea><Char>Børnene vil komme til at leve i fattigdom.</Char></Linea><Linea><Char>De vil ikke få råd til at gå til børnefødselsdage, for de kan ikke købe gaver til de andre børn; de vil ikke få råd til nogen fritidsaktiviteter; de vil ikke få råd til at komme med på lejrskoler; de vil ikke få råd til ordentlig ernæring til børnene, og dermed vil børnene heller ikke få så god en mulighed for at komme ind på videregående uddannelser, fordi deres hukommelse og mulighed for at koncentrere sig vil tage varig skade.</Char></Linea></Exitus><Exitus><Linea><Char>Alle disse ting, siger regeringen, kommer ikke til at ske, fordi folk kommer ud på arbejdsmarkedet.</Char></Linea><Linea><Char>Det er sådan set en fordel for børnene, for når forældrene kommer ud på arbejdsmarkedet, får de jo råd til at give børnene alle de ting, de har brug for.</Char></Linea><Linea><Char>Men der er det så bare, jeg spørger:</Char></Linea><Linea><Char>Hvis man nu ikke kan regne med, at hundrede procent af flygtningene kommer ud på arbejdsmarkedet – og jeg tror ikke engang regeringen vil regne med, at alle flygtninge kommer ud på arbejdsmarkedet – hvad har man så tænkt sig at gøre ved de marginaliserede børn?</Char></Linea><Linea><Char>Hvad har man tænkt sig at gøre ved de forældre, som kommer til at leve i fattigdom?</Char></Linea><Linea><Char>Hvordan har man tænkt sig at integrere de mennesker, som ikke kommer ud på arbejdsmarkedet?</Char></Linea><Linea><Char>Det vil jeg egentlig gerne have et svar på.</Char></Linea></Exitus></TekstGruppe></TaleSegment></Tale><Tale><Taler><MetaSpeakerMP><OratorFirstName>Pia</OratorFirstName><OratorLastName>Kjærsgaard</OratorLastName><GroupNameShort>DF</GroupNameShort><OratorRole>formand</OratorRole></MetaSpeakerMP><TalerTitel><Linea><Char>Formanden</Char><Char /></Linea></TalerTitel></Taler><TaleSegment><MetaSpeechSegment><LastModified>2016-02-24T12:25:52</LastModified><EdixiStatus>Typeset</EdixiStatus><StartDateTime>2015-08-21T10:23:03</StartDateTime><EndDateTime>2015-08-21T10:23:18</EndDateTime></MetaSpeechSegment><TekstGruppe><Exitus><Linea><Char>Tak.</Char></Linea><Linea><Char>Jeg skal lige høre, om hr.</Char></Linea><Linea><Char>Marcus Knuth markerede for en kort bemærkning.</Char></Linea><Linea><Char>For så skal ordføreren være så venlig at blive på talerstolen.</Char></Linea></Exitus></TekstGruppe></TaleSegment></Tale><Tale><Taler><MetaSpeakerMP><OratorFirstName>Marcus</OratorFirstName><OratorLastName>Knuth</OratorLastName><GroupNameShort>V</GroupNameShort><OratorRole>medlem</OratorRole></MetaSpeakerMP><TalerTitel><Linea><Char>Marcus Knuth</Char><Char> (V)</Char></Linea></TalerTitel></Taler><TaleSegment><MetaSpeechSegment><LastModified>2016-02-24T12:25:52</LastModified><EdixiStatus>Typeset</EdixiStatus><StartDateTime>2015-08-21T10:23:18</StartDateTime><EndDateTime>2015-08-21T10:23:52</EndDateTime></MetaSpeechSegment><TekstGruppe><Exitus><Linea><Char>Mange tak.</Char></Linea><Linea><Char>Jeg vil høre fru Ulla Sandbæk, om hun er enig i, at integrationen bedst sker på arbejdsmarkedet, og herunder om hun er bekendt med Rockwool Fondens forskningschef, Torben Tranæs', udtalelse om starthjælpen, som jo minder noget om den nye integrationsydelse, og som går på, at hvis man ser på den rene beskæftigelsesdel, må man sige, at det er en succes, at så mange flere er kommet ud på arbejdsmarkedet.</Char></Linea></Exitus></TekstGruppe></TaleSegment></Tale><Tale><Taler><MetaSpeakerMP><OratorFirstName>Pia</OratorFirstName><OratorLastName>Kjærsgaard</OratorLastName><GroupNameShort>DF</GroupNameShort><OratorRole>formand</OratorRole></MetaSpeakerMP><TalerTitel><Linea><Char>Formanden</Char><Char /></Linea></TalerTitel></Taler><TaleSegment><MetaSpeechSegment><LastModified>2016-02-24T12:25:52</LastModified><EdixiStatus>Typeset</EdixiStatus><StartDateTime>2015-08-21T10:23:52</StartDateTime><EndDateTime>2015-08-21T10:23:53</EndDateTime></MetaSpeechSegment><TekstGruppe><Exitus><Linea><Char>Tak.</Char></Linea><Linea><Char>Ordføreren.</Char></Linea></Exitus></TekstGruppe></TaleSegment></Tale><Tale><Taler><MetaSpeakerMP><OratorFirstName>Ulla</OratorFirstName><OratorLastName>Sandbæk</OratorLastName><GroupNameShort>ALT</GroupNameShort><OratorRole>medlem</OratorRole></MetaSpeakerMP><TalerTitel><Linea><Char>Ulla Sandbæk</Char><Char> (ALT)</Char></Linea></TalerTitel></Taler><TaleSegment><MetaSpeechSegment><LastModified>2016-02-24T12:25:52</LastModified><EdixiStatus>Typeset</EdixiStatus><StartDateTime>2015-08-21T10:23:53</StartDateTime><EndDateTime>2015-08-21T10:25:25</EndDateTime></MetaSpeechSegment><TekstGruppe><Exitus><Linea><Char>Tak.</Char></Linea><Linea><Char>Jeg vil godt tage det sidste spørgsmål om Rockwool Fonden først.</Char></Linea><Linea><Char>Rockwool Fonden gjorde jo udtrykkeligt opmærksom på, at der de første 2 år stort set ikke var nogen, der kom ud på arbejdsmarkedet.</Char></Linea><Linea><Char>Derimod var der kvinder, som forlod arbejdsmarkedet, og som aldrig nogen sinde kom tilbage på arbejdsmarkedet igen, så man marginaliserede gruppen af indvandrerkvinder, som ifølge deres traditioner i forvejen har svært ved at komme ud på arbejdsmarkedet.</Char></Linea><Linea><Char>Efter 4 år var der en lille stigning på 9 pct.</Char></Linea><Linea><Char>af dem, der kom ud på arbejdsmarkedet.</Char></Linea><Linea><Char>Så jeg synes, at jeg kan bruge Rockwool Fondens undersøgelse til at komme med det modsatte argument af det, som hr.</Char></Linea><Linea><Char>Magnus Heunicke bruger.</Char></Linea></Exitus><Exitus><Linea><Char>Spørgsmålet er så, om jeg er enig i, at det er godt at blive integreret via arbejdsmarkedet.</Char></Linea><Linea><Char>Det er jeg jo fuldstændig enig i, og derfor havde jeg sådan ønsket, at regeringen var kommet med nogle helt andre forslag til at få flygtninge ud på arbejdsmarkedet end at sætte en ydelse, som i forvejen var lav, ned, altså til en fattigdomsydelse.</Char></Linea><Linea><Char>Der er jo mange ting, man kan gøre for at få folk ud på arbejdsmarkedet.</Char></Linea><Linea><Char>Bl.a.</Char></Linea><Linea><Char>har de på Bornholm meget gode erfaringer med at fordele flygtningene.</Char></Linea><Linea><Char>Man kan allerede, når de kommer i flygtningelejr, kompetencebestemme dem og sende dem derhen, hvor kompetencerne er.</Char></Linea><Linea><Char>I dag bliver flygtningene sendt hen til en kommune, hvor de overhovedet ikke bliver efterspurgt.</Char></Linea><Linea><Char>Man kunne jo lynhurtigt lave ekstrauddannelse, og man kan lave mange, mange andre ting for at integrere flygtninge på arbejdsmarkedet.</Char></Linea><Linea><Char>Og det vil jeg personligt prøve at komme med et forslag til.</Char></Linea></Exitus></TekstGruppe></TaleSegment></Tale><Tale><Taler><MetaSpeakerMP><OratorFirstName>Pia</OratorFirstName><OratorLastName>Kjærsgaard</OratorLastName><GroupNameShort>DF</GroupNameShort><OratorRole>formand</OratorRole></MetaSpeakerMP><TalerTitel><Linea><Char>Formanden</Char><Char /></Linea></TalerTitel></Taler><TaleSegment><MetaSpeechSegment><LastModified>2016-02-24T12:25:52</LastModified><EdixiStatus>Typeset</EdixiStatus><StartDateTime>2015-08-21T10:25:25</StartDateTime><EndDateTime>2015-08-21T10:25:29</EndDateTime></MetaSpeechSegment><TekstGruppe><Exitus><Linea><Char>Tak.</Char></Linea><Linea><Char>Og det er ikke hr.</Char></Linea><Linea><Char>Magnus Heunicke, men hr.</Char></Linea><Linea><Char>Marcus Knuth.</Char></Linea></Exitus><Exitus><Linea><Char>Værsgo for den næste korte bemærkning.</Char></Linea></Exitus></TekstGruppe></TaleSegment></Tale><Tale><Taler><MetaSpeakerMP><OratorFirstName>Marcus</OratorFirstName><OratorLastName>Knuth</OratorLastName><GroupNameShort>V</GroupNameShort><OratorRole>medlem</OratorRole></MetaSpeakerMP><TalerTitel><Linea><Char>Marcus Knuth</Char><Char> (V)</Char></Linea></TalerTitel></Taler><TaleSegment><MetaSpeechSegment><LastModified>2016-02-24T12:25:52</LastModified><EdixiStatus>Typeset</EdixiStatus><StartDateTime>2015-08-21T10:25:29</StartDateTime><EndDateTime>2015-08-21T10:26:11</EndDateTime></MetaSpeechSegment><TekstGruppe><Exitus><Linea><Char>Tak.</Char></Linea><Linea><Char>Jeg er glad for, at vi er enige om, at integrationen bedst sker på arbejdsmarkedet.</Char></Linea><Linea><Char>Så er det også værd at bemærke i forhold til starthjælpen, at der med den her nye integrationsydelse er andre tiltag såsom som en sprogbonus, der skal gøre det endnu mere attraktivt at lære dansk og komme ud på arbejdsmarkedet.</Char></Linea><Linea><Char>Så hvis man kigger på mere nutidige anbefalinger i forhold til Rockwool Fonden, kan man se, at vi har Dansk Arbejdsgiverforening, der har været ude at anbefale det her lovforslag som noget, der vil øge integrationen, og noget, som vil få flere ud på arbejdsmarkedet.</Char></Linea><Linea><Char>Jeg vil høre, om fru Ulla Sandbæk er bekendt med Dansk Arbejdsgiverforenings anbefaling.</Char></Linea></Exitus></TekstGruppe></TaleSegment></Tale><Tale><Taler><MetaSpeakerMP><OratorFirstName>Pia</OratorFirstName><OratorLastName>Kjærsgaard</OratorLastName><GroupNameShort>DF</GroupNameShort><OratorRole>formand</OratorRole></MetaSpeakerMP><TalerTitel><Linea><Char>Formanden</Char><Char /></Linea></TalerTitel></Taler><TaleSegment><MetaSpeechSegment><LastModified>2016-02-24T12:25:52</LastModified><EdixiStatus>Typeset</EdixiStatus><StartDateTime>2015-08-21T10:26:11</StartDateTime><EndDateTime>2015-08-21T10:26:12</EndDateTime></MetaSpeechSegment><TekstGruppe><Exitus><Linea><Char>Tak.</Char></Linea><Linea><Char>Ordføreren.</Char></Linea></Exitus></TekstGruppe></TaleSegment></Tale><Tale><Taler><MetaSpeakerMP><OratorFirstName>Ulla</OratorFirstName><OratorLastName>Sandbæk</OratorLastName><GroupNameShort>ALT</GroupNameShort><OratorRole>medlem</OratorRole></MetaSpeakerMP><TalerTitel><Linea><Char>Ulla Sandbæk</Char><Char> (ALT)</Char></Linea></TalerTitel></Taler><TaleSegment><MetaSpeechSegment><LastModified>2016-02-24T12:25:52</LastModified><EdixiStatus>Typeset</EdixiStatus><StartDateTime>2015-08-21T10:26:12</StartDateTime><EndDateTime>2015-08-21T10:26:57</EndDateTime></MetaSpeechSegment><TekstGruppe><Exitus><Linea><Char>Ja, den er jeg i høj grad bekendt med.</Char></Linea><Linea><Char>Jeg var en af dem, som anbefalede, at vi fik nogle eksperter kaldt ind i udvalget.</Char></Linea><Linea><Char>Dansk Arbejdsgiverforening var en af dem.</Char></Linea><Linea><Char>Jeg hørte på deres argumentation, og det undrede mig, at deres argumentation var, at det skulle kunne betale sig at arbejde.</Char></Linea><Linea><Char>Det er jo ikke det, som er på spil her, altså om det kan betale sig eller ikke kan betale sig at arbejde.</Char></Linea><Linea><Char>Det, der er på spil, er, om en flygtning, som kommer til dette land, kan komme ud på arbejdsmarkedet, om der er en efterspørgsel på arbejdsmarkedet efter de kompetencer, som flygtningen kommer med, og om det er realistisk, at en flygtning kommer ud på arbejdsmarkedet.</Char></Linea><Linea><Char>Så at det, at det skulle kunne betale sig at arbejde, bruges som hovedargumentation for, at det her er et godt forslag, fatter jeg simpelt hen overhovedet ikke.</Char></Linea></Exitus></TekstGruppe></TaleSegment></Tale><Tale><Taler><MetaSpeakerMP><OratorFirstName>Pia</OratorFirstName><OratorLastName>Kjærsgaard</OratorLastName><GroupNameShort>DF</GroupNameShort><OratorRole>formand</OratorRole></MetaSpeakerMP><TalerTitel><Linea><Char>Formanden</Char><Char /></Linea></TalerTitel></Taler><TaleSegment><MetaSpeechSegment><LastModified>2016-02-24T12:25:52</LastModified><EdixiStatus>Typeset</EdixiStatus><StartDateTime>2015-08-21T10:26:57</StartDateTime><EndDateTime>2015-08-21T10:27:07</EndDateTime></MetaSpeechSegment><TekstGruppe><Exitus><Linea><Char>Tak til ordføreren.</Char></Linea><Linea><Char>Så er det den næste ordfører, og det er fru Sofie Carsten Nielsen, Radikale Venstre.</Char></Linea><Linea><Char>Værsgo.</Char></Linea></Exitus></TekstGruppe></TaleSegment></Tale><Tale><Taler><MetaSpeakerMP><OratorFirstName>Sofie Carsten</OratorFirstName><OratorLastName>Nielsen</OratorLastName><GroupNameShort>RV</GroupNameShort><OratorRole>medlem</OratorRole></MetaSpeakerMP><TalerTitel><Linea><Char>Sofie Carsten Nielsen</Char><Char> (RV)</Char></Linea></TalerTitel></Taler><TaleType><Linea><Char>Ordfører</Char></Linea></TaleType><TaleSegment><MetaSpeechSegment><LastModified>2016-02-24T12:25:52</LastModified><EdixiStatus>Typeset</EdixiStatus><StartDateTime>2015-08-21T10:27:07</StartDateTime><EndDateTime>2015-08-21T10:29:39</EndDateTime></MetaSpeechSegment><TekstGruppe><Exitus><Linea><Char>Tak for ordet.</Char></Linea><Linea><Char>Jeg er meget enig med de foregående ordførere.</Char></Linea><Linea><Char>Jeg synes, at fru Johanne Schmidt-Nielsen gennemgik en række af detaljerne rigtig godt.</Char></Linea></Exitus><Exitus><Linea><Char>Hele logikken i det her lovforslag er øjensynlig, at flygtninge kommer til Danmark for at nasse på samfundet.</Char></Linea><Linea><Char>Det er også det, som kommer til udtryk i hr.</Char></Linea><Linea><Char>Martin Henriksens spørgsmål, sådan som jeg opfatter dem, altså at flygtninge kommer for at få del i danske ydelser.</Char></Linea><Linea><Char>Og jeg synes, at der i den her debat mangler en skelnen mellem flygtninge, herunder hvilke mennesker vi anerkender som flygtninge, og andre, som rejser fra deres land for at få bedre vilkår, og som vi jo alle sammen godt ved at det her ikke handler om, for dem bevilger vi ikke asyl.</Char></Linea></Exitus><Exitus><Linea><Char>Det her forslag om en lavere såkaldt integrationsydelse vil medføre fattigdom, isolation og marginalisering af de grupper, de flygtninge, som modtager ydelsen, og som vi alle sammen, tror jeg, ønsker skal få mulighed for at vende tilbage til deres land, men som vi også håber vi kan få i arbejde, når de er her.</Char></Linea><Linea><Char>For i alle henseender vil det jo gøre dem bedre i stand til at bidrage, skulle de få mulighed for at vende tilbage til de lande, som lige nu er hærget af krig.</Char></Linea></Exitus><Exitus><Linea><Char>Så jeg og Radikale Venstre er af den opfattelse, at den her ydelse ikke handler om integration, selv om man faktisk kalder det en integrationsydelse.</Char></Linea><Linea><Char>Det handler om at undgå det og marginalisere de mennesker, der skal modtage den.</Char></Linea><Linea><Char>Så jeg synes sådan set, det er en hån at kalde det en integrationsydelse, og derfor stemmer vi selvfølgelig imod i Radikale Venstre.</Char></Linea></Exitus></TekstGruppe></TaleSegment></Tale><Tale><Taler><MetaSpeakerMP><OratorFirstName>Pia</OratorFirstName><OratorLastName>Kjærsgaard</OratorLastName><GroupNameShort>DF</GroupNameShort><OratorRole>formand</OratorRole></MetaSpeakerMP><TalerTitel><Linea><Char>Formanden</Char><Char /></Linea></TalerTitel></Taler><TaleSegment><MetaSpeechSegment><LastModified>2016-02-24T12:25:52</LastModified><EdixiStatus>Typeset</EdixiStatus><StartDateTime>2015-08-21T10:29:39</StartDateTime><EndDateTime>2015-08-21T10:30:03</EndDateTime></MetaSpeechSegment><TekstGruppe><Exitus><Linea><Char>Tak til ordføreren fra Det Radikale Venstre.</Char></Linea><Linea><Char>Så er der en ny ordfører.</Char></Linea><Linea><Char>Hr.</Char></Linea><Linea><Char>Jacob Mark, Socialistisk Folkeparti, værsgo.</Char></Linea></Exitus></TekstGruppe></TaleSegment></Tale><Tale><Taler><MetaSpeakerMP><OratorFirstName>Jacob</OratorFirstName><OratorLastName>Mark</OratorLastName><GroupNameShort>SF</GroupNameShort><OratorRole>medlem</OratorRole></MetaSpeakerMP><TalerTitel><Linea><Char>Jacob Mark</Char><Char> (SF)</Char></Linea></TalerTitel></Taler><TaleType><Linea><Char>Ordfører</Char></Linea></TaleType><TaleSegment><MetaSpeechSegment><LastModified>2016-02-24T12:25:52</LastModified><EdixiStatus>Typeset</EdixiStatus><StartDateTime>2015-08-21T10:30:03</StartDateTime><EndDateTime>2015-08-21T10:34:40</EndDateTime></MetaSpeechSegment><TekstGruppe><Exitus><Linea><Char>Tak for ordet.</Char></Linea><Linea><Char>Vi kommer også til at stemme nej til det her forslag i SF.</Char></Linea><Linea><Char>Vi synes alligevel, der er sket noget siden førstebehandlingen.</Char></Linea><Linea><Char>Førstebehandlingen kom måske også lidt pludseligt for nogle af os efter folketingsvalget, og vi vil gerne sådan lige sætte nogle ord på nogle af de ting, vi synes der er kommet frem siden.</Char></Linea></Exitus><Exitus><Linea><Char>Først og fremmest hedder det her jo en integrationsydelse, men det mener vi faktisk ikke det er.</Char></Linea><Linea><Char>Vi bakker meget op om, at der skal være vellykket integration i Danmark, og på samrådet hørte jeg egentlig integrationsministeren sige, at det gør hun også.</Char></Linea><Linea><Char>Derfor håber jeg også, at man kan nå at få hende til at ændre mening.</Char></Linea></Exitus><Exitus><Linea><Char>Der er nogle ting i det her forslag, som vi mener er problematiske.</Char></Linea><Linea><Char>For det første er der den helt menneskelige del:</Char></Linea><Linea><Char>at det her vil skabe øget fattigdom i Danmark.</Char></Linea><Linea><Char>Det synes vi er synd, og det synes vi er forfærdeligt for de mennesker, der kommer.</Char></Linea><Linea><Char>Det betyder, at børn måske lige pludselig ikke kan gå til sport.</Char></Linea><Linea><Char>Det betyder, at forældre skal overveje, om de skal bruge penge på en flyverdragt eller at få et godt aftensmåltid.</Char></Linea><Linea><Char>Det er den ene del.</Char></Linea><Linea><Char>Det tror vi ikke på skaber god integration.</Char></Linea></Exitus><Exitus><Linea><Char>Den anden del er det her med sprog.</Char></Linea><Linea><Char>For SF er det helt afgørende, at når folk kommer til landet, lærer de hurtigt dansk, så lærer de hurtigt sproget.</Char></Linea><Linea><Char>Derfor mener vi også, at det er helt afgørende, at de kan komme på en uddannelse, at de kan få den her prøve, og at de ligesom kan bevise, at de kan dansk, så de også kan få den her sprogbonus.</Char></Linea><Linea><Char>Det er jo i øvrigt også et af ministerens argumenter for, at man kan leve under almindelige vilkår, ikke fattigdom.</Char></Linea></Exitus><Exitus><Linea><Char>Men det er jo kommet frem siden førstebehandlingen, at den her sprogbonus kan man jo kun få, hvis man tager sprogprøve 2, og for rigtig manges vedkommende starter de på sprogprøve 1, og så skal de selv betale de mange lektioner, hvis de vil op og bestå toeren.</Char></Linea><Linea><Char>Det er jo et problem, når man samtidig halverer deres ydelse.</Char></Linea><Linea><Char>Det her tror vi vil komme til at betyde, at der er rigtig mange, der ikke prioriterer deres danskundervisning.</Char></Linea><Linea><Char>Der er rigtig mange, der ikke kan prioritere deres danskundervisning, fordi de er nødt til at prioritere f.eks.</Char></Linea><Linea><Char>deres børn eller helt almindelige levevilkår.</Char></Linea><Linea><Char>Så det, der skulle være en integrationsydelse, betyder i virkeligheden, at folk kommer til landet og mister deres mulighed for at lære dansk, i hvert fald får forringet mulighed for at lære dansk.</Char></Linea></Exitus><Exitus><Linea><Char>Så er der det her argument med, at de jo skal lære dansk ude i virksomhederne.</Char></Linea><Linea><Char>Jeg kan godt stille mig sådan lidt kritisk ved det udsagn, at der bare skulle være jobs nok.</Char></Linea><Linea><Char>Jeg kommer selv fra en kommune, hvor vi har prøvet at få en masse flygtninge ud at arbejde, men det er altså bare svært.</Char></Linea><Linea><Char>De kan jo ikke bare lige gå ind i en virksomhed.</Char></Linea><Linea><Char>Der er også mange danskere, der ikke kan få jobs.</Char></Linea><Linea><Char>Tror vi så på, at folk, der kommer fra krig og nød, bare kan vade lige ind i en virksomhed og sige:</Char></Linea><Linea><Char>Jeg er klar, I kan bare tage mig, og jeg kan det hele?</Char></Linea><Linea><Char>Så hele forudsætningen for det her med, at de bare kan træde ind i en virksomhed og der er de jobs, kan jeg også godt sætte spørgsmålstegn ved.</Char></Linea></Exitus><Exitus><Linea><Char>Jeg synes heller ikke, at der er svaret på, hvor de job skal komme fra.</Char></Linea><Linea><Char>Men der vil vi selvfølgelig gerne hjælpe til med fremadrettet at skabe gode samarbejder mellem virksomheder og kommuner, så det håber jeg vi kan få en dialog om.</Char></Linea></Exitus><Exitus><Linea><Char>Den næste del, som er rigtig bekymrende, er, at den her integrationsydelse også betyder, at flygtninge nærmest ikke har råd til at betale deres bolig.</Char></Linea><Linea><Char>Det er for det første ikke værdigt for de mennesker, der kommer til landet, at de skal gå og overveje, om de overhovedet kan betale deres bolig, men for det andet stiller det jo landets kommuner i et kæmpe problem.</Char></Linea></Exitus><Exitus><Linea><Char>I dag i metroXpress på vej i S-toget læste jeg, at der simpelt hen er så mange kommuner, hvor de bor på hoteller, og jeg ved da også – igen ud fra min egen kommune – at lige nu sidder man og overvejer, om de nu overhovedet kan betale en husleje.</Char></Linea><Linea><Char>De har fået halveret deres indkomst, og de skal betale en husleje, hvor skal vi så placerer dem?</Char></Linea><Linea><Char>Det skal være i nogle lejligheder, de har råd til at betale.</Char></Linea></Exitus><Exitus><Linea><Char>Vi har nogle enkelte muligheder.</Char></Linea><Linea><Char>Der er de udsatte boligområder, hvor man egentlig ikke må placere dem eller skal placere dem, for det er dårligt for integrationen.</Char></Linea><Linea><Char>Men kommunerne har jo ikke råd til andet.</Char></Linea><Linea><Char>Så lige nu er der en masse kommuner, som rigtig gerne vil fremme integrationen, og er i vildrede, for de ved ikke, hvordan de skal få råd til de her mange boliger, og det betyder, at man i kommunerne sidder og overvejer at sætte dem ud i boligområder.</Char></Linea><Linea><Char>Jeg vil så gerne gå i dialog med integrationsministeren og spørge:</Char></Linea><Linea><Char>Tror man også, at det gavner integrationen, at man samler folk i boligområder, der i forvejen har problemer?</Char></Linea><Linea><Char>For det vil jo være konsekvensen af det her.</Char></Linea></Exitus><Exitus><Linea><Char>Så samlet set vil jeg jo gerne på SF's vegne stille mig til rådighed for en dialog om, hvordan vi kan sikre, at der er boliger til de her mennesker, hvordan vi hjælper kommunerne, for det hørte jeg også ministeren i pressen åbne op for.</Char></Linea><Linea><Char>Jeg vil gerne gå i en dialog om, hvordan vi kan sørge for, at de her mennesker hurtigt lærer dansk, så de får større forudsætninger for at komme ud i virksomheder, men sådan som det ligger lige nu, kan vi altså ikke bakke op om den her ydelse og det her lovforslag, for den her integrationsydelse er ikke en integrationsydelse.</Char></Linea><Linea><Char>For mig at se er det lige nu en eksklusionsydelse.</Char></Linea><Linea><Char>Tak.</Char></Linea></Exitus></TekstGruppe></TaleSegment></Tale><Tale><Taler><MetaSpeakerMP><OratorFirstName>Pia</OratorFirstName><OratorLastName>Kjærsgaard</OratorLastName><GroupNameShort>DF</GroupNameShort><OratorRole>formand</OratorRole></MetaSpeakerMP><TalerTitel><Linea><Char>Formanden</Char><Char /></Linea></TalerTitel></Taler><TaleSegment><MetaSpeechSegment><LastModified>2016-02-24T12:25:52</LastModified><EdixiStatus>Typeset</EdixiStatus><StartDateTime>2015-08-21T10:34:40</StartDateTime><EndDateTime>2015-08-21T10:34:52</EndDateTime></MetaSpeechSegment><TekstGruppe><Exitus><Linea><Char>Tak til ordføreren.</Char></Linea><Linea><Char>Er der flere, der ønsker at udtale sig?</Char></Linea></Exitus><Exitus><Linea><Char>Da det ikke er tilfældet, er forhandlingen sluttet, og vi går til afstemning.</Char></Linea></Exitus></TekstGruppe></TaleSegment></Tale></Aktivitet><Aktivitet><Rubrica><Linea><Char>Afstemning</Char></Linea></Rubrica><Tale><Taler><MetaSpeakerMP><OratorFirstName>Pia</OratorFirstName><OratorLastName>Kjærsgaard</OratorLastName><GroupNameShort>DF</GroupNameShort><OratorRole>formand</OratorRole></MetaSpeakerMP><TalerTitel><Linea><Char>Formanden</Char><Char /></Linea></TalerTitel></Taler><TaleSegment><MetaSpeechSegment><LastModified>2016-02-24T12:25:52</LastModified><EdixiStatus>Typeset</EdixiStatus><StartDateTime>2015-08-21T10:34:52</StartDateTime><EndDateTime>2015-08-21T10:35:21</EndDateTime></MetaSpeechSegment><TekstGruppe><Exitus><Linea><Char>Ønskes der afstemning om ændringsforslag nr.</Char></Linea><Linea><Char>1-16, tiltrådt af udvalget?</Char></Linea></Exitus><Exitus><Linea><Char>De er vedtaget.</Char></Linea></Exitus></TekstGruppe><TekstGruppe><Exitus><Linea><Char>Jeg foreslår, at lovforslaget går direkte til tredje behandling uden fornyet udvalgsbehandling.</Char></Linea><Linea><Char>Hvis ingen gør indsigelse, betragter jeg dette som vedtaget.</Char></Linea></Exitus><Exitus><Linea><Char>Det er vedtaget.</Char></Linea></Exitus></TekstGruppe></TaleSegment></Tale></Aktivitet></DagsordenPunkt><DagsordenPunkt><MetaFTAgendaItem><ItemNo>5</ItemNo><FTCase /><FTCaseNumber>5</FTCaseNumber><FTCaseType>L</FTCaseType><FTCaseStage>BEH2</FTCaseStage><ShortTitle>2. behandling af L 5: Om genindførelse af boligjobordningen.</ShortTitle></MetaFTAgendaItem><PunktTekst><PreTekst><Exitus><Linea><Char>Det næste punkt på dagsordenen er:</Char></Linea></Exitus></PreTekst><Exitus><Linea><Char>5) 2. behandling af lovforslag nr. L 5:</Char></Linea></Exitus><Exitus><Linea><Char>Forslag til lov om ændring af ligningsloven.
(Genindførelse af boligjobordningen).</Char></Linea></Exitus><Exitus><Linea><Char>Af skatteministeren (Karsten Lauritzen).</Char></Linea></Exitus><Exitus><Linea><Char>(Fremsættelse 03.07.2015. 1. behandling 03.07.2015. Betænkning 18.08.2015).</Char></Linea></Exitus></PunktTekst><Aktivitet><Rubrica><Linea><Char>Forhandling</Char></Linea></Rubrica><Tale><Taler><MetaSpeakerMP><OratorFirstName>Pia</OratorFirstName><OratorLastName>Kjærsgaard</OratorLastName><GroupNameShort>DF</GroupNameShort><OratorRole>formand</OratorRole></MetaSpeakerMP><TalerTitel><Linea><Char>Formanden</Char><Char /></Linea></TalerTitel></Taler><TaleSegment><MetaSpeechSegment><LastModified>2016-02-24T12:25:52</LastModified><EdixiStatus>Typeset</EdixiStatus><StartDateTime>2015-08-21T10:35:21</StartDateTime><EndDateTime>2015-08-21T10:35:39</EndDateTime></MetaSpeechSegment><TekstGruppe><Exitus><Linea><Char>Der er ikke stillet ændringsforslag.</Char></Linea></Exitus><Exitus><Linea><Char>Er der nogen, der ønsker at udtale sig?</Char></Linea></Exitus><Exitus><Linea><Char>Det er bedre at trykke på knappen end at pifte.</Char></Linea></Exitus><Exitus><Linea><Char>Hr.</Char></Linea><Linea><Char>Rune Lund fra Enhedslisten.</Char></Linea><Linea><Char>Værsgo.</Char></Linea></Exitus></TekstGruppe></TaleSegment></Tale><Tale><Taler><MetaSpeakerMP><OratorFirstName>Rune</OratorFirstName><OratorLastName>Lund</OratorLastName><GroupNameShort>EL</GroupNameShort><OratorRole>medlem</OratorRole></MetaSpeakerMP><TalerTitel><Linea><Char>Rune Lund</Char><Char> (EL)</Char></Linea></TalerTitel></Taler><TaleType><Linea><Char>Ordfører</Char></Linea></TaleType><TaleSegment><MetaSpeechSegment><LastModified>2016-02-24T12:25:52</LastModified><EdixiStatus>Typeset</EdixiStatus><StartDateTime>2015-08-21T10:35:39</StartDateTime><EndDateTime>2015-08-21T10:39:18</EndDateTime></MetaSpeechSegment><TekstGruppe><Exitus><Linea><Char>Tak.</Char></Linea><Linea><Char>Jeg vil gerne beklage, men der er kommet en ny knap, siden jeg var herinde sidst for 8 år siden.</Char></Linea><Linea><Char>(</Char><Char>Formanden</Char><Char>:</Char></Linea><Linea><Char>Vi har nu aldrig piftet, vil jeg så sige).</Char></Linea></Exitus><Exitus><Linea><Char>Det her lovforslag har jo været til første behandling, men der har jo været en debat om lovforslaget mellem førstebehandlingen og den anden behandling, som vi har i dag.</Char></Linea><Linea><Char>Det, der jo er kommet frem, er det, som også blev klart ved førstebehandlingen, nemlig at det her er et lovforslag med en klar asocial profil, som omfordeler fra bund til top.</Char></Linea><Linea><Char>Det er jo sådan, at det er SOSU-assistenten, det er lagerarbejderen, det er butiksassistenten, som via skattebilletten skal betale, for at folk med højere indkomster kan få lavet renoveringer eller få rengøringshjælp.</Char></Linea><Linea><Char>Det er altså en asocial ordning.</Char></Linea></Exitus><Exitus><Linea><Char>Det er jo også sådan, og det var jo også klart ved førstebehandlingen, at 80 pct.</Char></Linea><Linea><Char>af dem, der benytter den her ordning, er boligejere, og at fradraget har en markant social slagside, fordi det er sådan, at blandt de 3,5 millioner danskere med de laveste indkomster er det kun 8 ud af 100, der bruger fradraget, men blandt de 1.000 rigeste danskere er det 4 ud af 10.</Char></Linea><Linea><Char>Så den sociale slagside er stærk.</Char></Linea></Exitus><Exitus><Linea><Char>Det er også sådan, at det grønne element i aftalen, hvilket også er blevet klart i den debat, der har været mellem første- og andenbehandlingen, er meget lille.</Char></Linea><Linea><Char>Det var sådan, at det i 2014 kun var omkring 30 pct.</Char></Linea><Linea><Char>eller mindre end 30 pct.</Char></Linea><Linea><Char>af fradraget, der gik til energiforbedringer.</Char></Linea></Exitus><Exitus><Linea><Char>Der er så sket det interessante i debatten, at skatteministeren mellem den første behandling, der har været, og den anden behandling, vi har i dag, jo faktisk har været ude og indrømme, at det har været en dyr og ineffektiv ordning.</Char></Linea><Linea><Char>Det har skatteministeren både gjort i pressen og på det samråd, der har været afholdt i den her uge.</Char></Linea><Linea><Char>Det synes jeg egentlig godt at vi kunne forfølge lidt her i Folketingssalen i dag.</Char></Linea><Linea><Char>Det er jo dagen, hvor der er blevet indgået en regionsaftale, som kræver, hvis økonomien skal hænge sammen, at de ansatte skal løbe endnu stærkere, end de allerede gør i forvejen.</Char></Linea><Linea><Char>I den situation vælger man så fra regeringens side at sige:</Char></Linea><Linea><Char>Vi vil bruge 1 mia.</Char></Linea><Linea><Char>kr.</Char></Linea><Linea><Char>på en asocial, ikkegrøn og jobineffektiv ordning, som skaber utrolig få jobs.</Char></Linea><Linea><Char>Det er samtidig med, at der ikke er nok penge, synes regeringen, til at prioritere vores alle sammens offentlige sundhedsvæsen.</Char></Linea></Exitus><Exitus><Linea><Char>Jeg synes ærlig talt, at det er meget beskæmmende, især når skatteministeren har været ude at indrømme, at det er en dyr og ineffektiv ordning, at skatteministeren så ikke i dag kommenterer på, hvorfor regeringen bliver ved med at opretholde støtten til den her ordning, når den ikke skaber jobs, når den ikke er grønt, og når den er asocial.</Char></Linea><Linea><Char>Jeg synes, at det kunne være rart, hvis regeringen, hvis man vil blive ved med at opretholde støtten, her fra Folketingets talerstol klart og tydeligt siger:</Char></Linea><Linea><Char>Ja, den er dyr og ineffektiv; ja, det giver ikke mening; ja, vi kunne bruge pengene meget mere fornuftigt andre steder, men vi opretholder den alligevel, fordi ...</Char></Linea><Linea><Char>Og det er så der, vi godt kunne tænke os, at skatteministeren kom med en forklaring.</Char></Linea><Linea><Char>Tak for ordet.</Char></Linea></Exitus></TekstGruppe></TaleSegment></Tale><Tale><Taler><MetaSpeakerMP><OratorFirstName>Pia</OratorFirstName><OratorLastName>Kjærsgaard</OratorLastName><GroupNameShort>DF</GroupNameShort><OratorRole>formand</OratorRole></MetaSpeakerMP><TalerTitel><Linea><Char>Formanden</Char><Char /></Linea></TalerTitel></Taler><TaleSegment><MetaSpeechSegment><LastModified>2016-02-24T12:25:52</LastModified><EdixiStatus>Typeset</EdixiStatus><StartDateTime>2015-08-21T10:39:18</StartDateTime><EndDateTime>2015-08-21T10:39:39</EndDateTime></MetaSpeechSegment><TekstGruppe><Exitus><Linea><Char>Tak til ordføreren.</Char></Linea><Linea><Char>Er der flere, der ønsker at udtale sig?</Char></Linea></Exitus><Exitus><Linea><Char>Da det ikke er tilfældet, er forhandlingen sluttet.</Char></Linea></Exitus></TekstGruppe><TekstGruppe><Exitus><Linea><Char>Jeg foreslår, at lovforslaget går direkte til tredje behandling uden fornyet udvalgsbehandling, og hvis ingen gør indsigelse, betragter jeg dette som vedtaget.</Char></Linea></Exitus><Exitus><Linea><Char>Det er vedtaget.</Char></Linea></Exitus></TekstGruppe></TaleSegment></Tale></Aktivitet></DagsordenPunkt><DagsordenPunkt><MetaFTAgendaItem><ItemNo>6</ItemNo><FTCase /><FTCaseNumber>6</FTCaseNumber><FTCaseType>L</FTCaseType><FTCaseStage>BEH2</FTCaseStage><ShortTitle>2. behandling af L 6: Om ændring af rentetillæg for afregning af selskabsskat og begrænsning af indestående på skattekontoen.</ShortTitle></MetaFTAgendaItem><PunktTekst><PreTekst><Exitus><Linea><Char>Det næste punkt på dagsordenen er:</Char></Linea></Exitus></PreTekst><Exitus><Linea><Char>6) 2. behandling af lovforslag nr. L 6:</Char></Linea></Exitus><Exitus><Linea><Char>Forslag til lov om ændring af opkrævningsloven og selskabsskatteloven.
(Ændring af rentetillæg for afregning af selskabsskat og begrænsning af indestående på skattekontoen m.v.).</Char></Linea></Exitus><Exitus><Linea><Char>Af skatteministeren (Karsten Lauritzen).</Char></Linea></Exitus><Exitus><Linea><Char>(Fremsættelse 03.07.2015. 1. behandling 03.07.2015. Betænkning 18.08.2015).</Char></Linea></Exitus></PunktTekst><Aktivitet><Rubrica><Linea><Char>Forhandling</Char></Linea></Rubrica><Tale><Taler><MetaSpeakerMP><OratorFirstName>Pia</OratorFirstName><OratorLastName>Kjærsgaard</OratorLastName><GroupNameShort>DF</GroupNameShort><OratorRole>formand</OratorRole></MetaSpeakerMP><TalerTitel><Linea><Char>Formanden</Char><Char /></Linea></TalerTitel></Taler><TaleSegment><MetaSpeechSegment><LastModified>2016-02-24T12:25:52</LastModified><EdixiStatus>Typeset</EdixiStatus><StartDateTime>2015-08-21T10:39:39</StartDateTime><EndDateTime>2015-08-21T10:40:10</EndDateTime></MetaSpeechSegment><TekstGruppe><Exitus><Linea><Char>Der er ikke stillet ændringsforslag.</Char></Linea></Exitus><Exitus><Linea><Char>Jeg skal høre, om der er nogen, der ønsker at udtale sig.</Char></Linea></Exitus><Exitus><Linea><Char>Da det ikke er tilfældet, er forhandlingen sluttet.</Char></Linea></Exitus></TekstGruppe><TekstGruppe><Exitus><Linea><Char>Jeg foreslår, at lovforslaget går direkte til tredje behandling uden fornyet udvalgsbehandling, og hvis ingen gør indsigelse, betragter jeg dette som vedtaget.</Char></Linea></Exitus><Exitus><Linea><Char>Det er vedtaget.</Char></Linea></Exitus></TekstGruppe></TaleSegment></Tale></Aktivitet></DagsordenPunkt><DagsordenPunkt><MetaFTAgendaItem><ItemNo>7</ItemNo><FTCase /><FTCaseNumber>7</FTCaseNumber><FTCaseType>L</FTCaseType><FTCaseStage>BEH2</FTCaseStage><ShortTitle>2. behandling af L 7: Om optjeningsprincippet for ret til børnetilskud og børne- og ungeydelse for flygtninge.</ShortTitle></MetaFTAgendaItem><PunktTekst><PreTekst><Exitus><Linea><Char>Det næste punkt på dagsordenen er:</Char></Linea></Exitus></PreTekst><Exitus><Linea><Char>7) 2. behandling af lovforslag nr. L 7:</Char></Linea></Exitus><Exitus><Linea><Char>Forslag til lov om ændring af lov om børnetilskud og forskudsvis udbetaling af børnebidrag og lov om en børne- og ungeydelse. (Genindførelse af optjeningsprincippet for ret til børnetilskud og børne- og ungeydelse for flygtninge).</Char></Linea></Exitus><Exitus><Linea><Char>Af skatteministeren (Karsten Lauritzen).</Char></Linea></Exitus><Exitus><Linea><Char>(Fremsættelse 03.07.2015. 1. behandling 03.07.2015. Betænkning 19.08.2015).</Char></Linea></Exitus></PunktTekst><Aktivitet><Rubrica><Linea><Char>Forhandling</Char></Linea></Rubrica><Tale><Taler><MetaSpeakerMP><OratorFirstName>Pia</OratorFirstName><OratorLastName>Kjærsgaard</OratorLastName><GroupNameShort>DF</GroupNameShort><OratorRole>formand</OratorRole></MetaSpeakerMP><TalerTitel><Linea><Char>Formanden</Char><Char /></Linea></TalerTitel></Taler><TaleSegment><MetaSpeechSegment><LastModified>2016-02-24T12:25:52</LastModified><EdixiStatus>Typeset</EdixiStatus><StartDateTime>2015-08-21T10:40:10</StartDateTime><EndDateTime>2015-08-21T10:40:45</EndDateTime></MetaSpeechSegment><TekstGruppe><Exitus><Linea><Char>Der er ikke stillet ændringsforslag.</Char></Linea></Exitus><Exitus><Linea><Char>Er der nogen, der ønsker at udtale sig?</Char></Linea></Exitus><Exitus><Linea><Char>Da det ikke er tilfældet, er forhandlingen sluttet.</Char></Linea></Exitus></TekstGruppe><TekstGruppe><Exitus><Linea><Char>Jeg foreslår, at lovforslaget går direkte til tredje behandling uden fornyet udvalgsbehandling.</Char></Linea><Linea><Char>Hvis ingen gør indsigelse, betragter jeg dette som vedtaget.</Char></Linea></Exitus><Exitus><Linea><Char>Det er vedtaget.</Char></Linea></Exitus></TekstGruppe></TaleSegment></Tale></Aktivitet></DagsordenPunkt><DagsordenPunkt><MetaFTAgendaItem><ItemNo>8</ItemNo><FTCase /><FTCaseNumber>5</FTCaseNumber><FTCaseType>B</FTCaseType><FTCaseStage>BEH1</FTCaseStage><ShortTitle>1. behandling af B 5: Om nedlæggelse og sammenlægning af visse stående udvalg.</ShortTitle></MetaFTAgendaItem><PunktTekst><PreTekst><Exitus><Linea><Char>Det sidste punkt på dagsordenen er:</Char></Linea></Exitus></PreTekst><Exitus><Linea><Char>8) 1. behandling af beslutningsforslag nr. B 5:</Char></Linea></Exitus><Exitus><Linea><Char>Forslag til folketingsbeslutning om ændring af forretningsorden for Folketinget. (Nedlæggelse og sammenlægning af visse stående udvalg).</Char></Linea></Exitus><Exitus><Linea><Char>(Forslag som fremsat (i betænkning) 03.07.2015. Anmeldelse (i salen) 03.07.2015).</Char></Linea></Exitus></PunktTekst><Aktivitet><Rubrica><Linea><Char>Forhandling</Char></Linea></Rubrica><Tale><Taler><MetaSpeakerMP><OratorFirstName>Pia</OratorFirstName><OratorLastName>Kjærsgaard</OratorLastName><GroupNameShort>DF</GroupNameShort><OratorRole>formand</OratorRole></MetaSpeakerMP><TalerTitel><Linea><Char>Formanden</Char><Char /></Linea></TalerTitel></Taler><TaleSegment><MetaSpeechSegment><LastModified>2016-02-24T12:25:52</LastModified><EdixiStatus>Typeset</EdixiStatus><StartDateTime>2015-08-21T10:40:45</StartDateTime><EndDateTime>2015-08-21T10:41:28</EndDateTime></MetaSpeechSegment><TekstGruppe><Exitus><Linea><Char>Forhandlingen er åbnet.</Char></Linea><Linea><Char>Er der nogen, der ønsker at udtale sig?</Char></Linea></Exitus><Exitus><Linea><Char>Det er der ikke.</Char></Linea></Exitus></TekstGruppe><TekstGruppe><Exitus><Linea><Char>Jeg foreslår, at forslaget går direkte til anden og sidste behandling, og hvis ingen gør indsigelse, betragter jeg dette som vedtaget.</Char></Linea></Exitus><Exitus><Linea><Char>Det er vedtaget.</Char></Linea></Exitus></TekstGruppe></TaleSegment></Tale></Aktivitet></DagsordenPunkt><DagsordenPunkt><MetaFTAgendaItem><ItemNo>0</ItemNo><FTCase /><FTCaseNumber /><FTCaseType>FM</FTCaseType><FTCaseStage /><ShortTitle>Punkt 0</ShortTitle></MetaFTAgendaItem><PunktTekst><Exitus><Linea><Char /></Linea></Exitus></PunktTekst><Aktivitet><Rubrica><Linea><Char>Meddelelser fra formanden</Char></Linea></Rubrica><Tale><Taler><MetaSpeakerMP><OratorFirstName>Pia</OratorFirstName><OratorLastName>Kjærsgaard</OratorLastName><GroupNameShort>DF</GroupNameShort><OratorRole>formand</OratorRole></MetaSpeakerMP><TalerTitel><Linea><Char>Formanden</Char><Char /></Linea></TalerTitel></Taler><TaleSegment><MetaSpeechSegment><LastModified>2016-02-24T12:25:52</LastModified><EdixiStatus>Typeset</EdixiStatus><StartDateTime>2015-08-21T10:41:28</StartDateTime><EndDateTime>2015-08-21T10:42:52</EndDateTime></MetaSpeechSegment><TekstGruppe><Exitus><Linea><Char>Venstres folketingsgruppe har meddelt mig, at den til Danmarks Nationalbanks repræsentantskab har udpeget medlemmer af Folketinget Jacob Jensen og Jakob Ellemann-Jensen som medlemmer for den resterende del af indeværende funktionsperiode i stedet for Lars Løkke Rasmussen og Inger Støjberg, som er udnævnt som henholdsvis statsminister og udlændinge-, integrations- og boligminister.</Char></Linea></Exitus></TekstGruppe><TekstGruppe><Exitus><Linea><Char>Derudover har Radikale Venstre meddelt mig, at de har udpeget medlem af Folketinget Morten Østergaard som medlem af repræsentantskabet for den resterende del af indeværende funktionsperiode i stedet for Camilla Hersom, som er udtrådt af Folketinget.</Char></Linea></Exitus></TekstGruppe><TekstGruppe><Exitus><Linea><Char>Venstres folketingsgruppe har meddelt mig, at den pr.</Char></Linea><Linea><Char>28.</Char></Linea><Linea><Char>juli 2015 har udpeget medlem af Folketinget Søren Gade som statsrevisor i stedet for Kristian Jensen, der pr.</Char></Linea><Linea><Char>28.</Char></Linea><Linea><Char>juni 2015 er udnævnt som minister, og Jakob Ellemann-Jensen som stedfortræder i stedet for Inger Støjberg, der ligeledes pr.</Char></Linea><Linea><Char>28.</Char></Linea><Linea><Char>juni 2015 er udnævnt til minister.</Char></Linea></Exitus></TekstGruppe><TekstGruppe><Exitus><Linea><Char>Der er ikke mere at foretage i dette møde.</Char></Linea></Exitus></TekstGruppe><TekstGruppe><Exitus><Linea><Char>Folketingets næste møde afholdes onsdag den 26.</Char></Linea><Linea><Char>august 2015, kl.</Char></Linea><Linea><Char>13.00</Char></Linea></Exitus><Exitus><Linea><Char>Jeg henviser til den dagsorden, der fremgår af Folketingets hjemmeside.</Char></Linea></Exitus></TekstGruppe></TaleSegment></Tale></Aktivitet><Aktivitet><Tale><Taler><MetaSpeakerMP><OratorFirstName>MødeSlut</OratorFirstName><OratorLastName>MødeSlut</OratorLastName><GroupNameShort>MødeSlut</GroupNameShort><OratorRole>MødeSlut</OratorRole></MetaSpeakerMP><TalerTitel><Linea><Char /><Char /></Linea></TalerTitel></Taler><TaleSegment><MetaSpeechSegment><LastModified>2016-02-24T12:25:52</LastModified><EdixiStatus>Typeset</EdixiStatus><StartDateTime>2015-08-21T10:42:52</StartDateTime></MetaSpeechSegment><TekstGruppe><Exitus><Linea><Char>Mødet er hævet.</Char></Linea><Linea><Char>(Kl.</Char></Linea><Linea><Char>10:42).</Char></Linea></Exitus></TekstGruppe></TaleSegment></Tale></Aktivitet></DagsordenPunkt></Dokument>