<?xml version="1.0" encoding="utf-8"?><Dokument edixistatus="Foreløbig"><MetaMeeting><ParliamentarySession>20161</ParliamentarySession><ParliamentaryGroup>Folketinget</ParliamentaryGroup><MeetingNumber>900</MeetingNumber><DateOfSitting>2017-09-14T00:00:00</DateOfSitting><Location>Folketingssalen</Location><EdixiDocLocation>W:\20161\M900\</EdixiDocLocation><AudioFileFolder>X:\Arbor\FT2016\900\SALEN\</AudioFileFolder></MetaMeeting><TitelGruppe><Titel><Linea><Char>900. møde</Char></Linea></Titel><UnderTitel><Linea><Char>Torsdag den 14. september 2017 kl. 0.00</Char></Linea></UnderTitel></TitelGruppe><DagsordenPlan><Rubrica><Linea><Char>Dagsorden</Char></Linea></Rubrica><PunktTekst><Exitus><Linea><Char>1) Spørgetime med statsministeren.</Char></Linea></Exitus></PunktTekst><PunktTekst><Exitus><Linea><Char>2) Besvarelse af oversendte spørgsmål til ministrene (spørgetid).</Char></Linea></Exitus><Exitus><Linea><Char>(Se nedenfor).</Char></Linea></Exitus></PunktTekst><PunktTekst><Exitus><Linea><Char>3) 3. behandling af lovforslag nr. L 163:</Char></Linea></Exitus><Exitus><Linea><Char>Forslag til lov om 3. behandling.</Char></Linea></Exitus><Exitus><Linea><Char>Af transport-, bygnings- og boligministeren (Ole Birk Olesen).</Char></Linea></Exitus><Exitus><Linea><Char>(2. behandling 13.09.2017. 1. behandling 13.09.2017. Fremsættelse 13.09.2017).</Char></Linea></Exitus></PunktTekst><PunktTekst><Exitus><Linea><Char>4) 1. behandling af lovforslag nr. L 161:</Char></Linea></Exitus><Exitus><Linea><Char>Forslag til lov om hvor der optræder </Char><Char>m</Char><Char>2</Char><Char> i titlen.</Char></Linea></Exitus><Exitus><Linea><Char>Af energi-, forsynings- og klimaministeren (Lars Christian Lilleholt).</Char></Linea></Exitus><Exitus><Linea><Char>(Fremsættelse 13.09.2017).</Char></Linea></Exitus></PunktTekst><PunktTekst><Exitus><Linea><Char>5) 1. behandling af lovforslag nr. L 162:</Char></Linea></Exitus><Exitus><Linea><Char>Forslag til lov hvor der optræder </Char><Char>CO</Char><Char>2</Char><Char> i titlen.</Char></Linea></Exitus><Exitus><Linea><Char>Af energi-, forsynings- og klimaministeren (Lars Christian Lilleholt).</Char></Linea></Exitus><Exitus><Linea><Char>(Fremsættelse 13.09.2017).</Char></Linea></Exitus></PunktTekst><PunktTekst><Exitus><Linea><Char>6) Eventuelt: 1. behandling af lovforslag nr. L 164:</Char></Linea></Exitus><Exitus><Linea><Char>Forslag til lov som kun behandles med Tingets samtykke.</Char></Linea></Exitus><Exitus><Linea><Char>Af miljø- og fødevareministeren (Esben Lunde Larsen).</Char></Linea></Exitus><Exitus><Linea><Char>(Fremsættelse 13.09.2017).</Char></Linea></Exitus></PunktTekst><PunktTekst><Exitus><Linea><Char>7) 1. behandling af beslutningsforslag nr. B 95:</Char></Linea></Exitus><Exitus><Linea><Char>Forslag til folketingsbeslutning om test af beslutningsforslag. </Char></Linea></Exitus><Exitus><Linea><Char>Af Pernille Skipper (EL) og Nikolaj Villumsen (EL).</Char></Linea></Exitus><Exitus><Linea><Char>(Fremsættelse 13.09.2017).</Char></Linea></Exitus></PunktTekst><PunktTekst><Exitus><Linea><Char>8) Forespørgsel nr. F 49:</Char></Linea></Exitus><Exitus><Linea><Char>Forespørgsel til undervisningsministeren.</Char></Linea></Exitus><Exitus><Linea><Char>Af Pia Olsen Dyhr (SF) og Søren Espersen (DF).</Char></Linea></Exitus><Exitus><Linea><Char>(Fremme 13.09.2017. Anmeldelse 13.09.2017).</Char></Linea></Exitus></PunktTekst><PunktTekst><Exitus><Linea><Char>1) Til uddannelses- og forskningsministeren af:</Char></Linea></Exitus><Exitus><Linea><Char>Christine Antorini</Char><Char> (S)</Char></Linea></Exitus><Exitus><Linea><Char>Er ministeren enig i, at adgang til at kunne bruge internettet ved relevante eksamener på de videregående uddannelser skal forbydes, sådan som undervisningsministeren ønsker </Char><Char>m</Char><Char>2</Char><Char> det på ungdomsuddannelserne?</Char></Linea></Exitus><Exitus><Linea><Char>(Spm. nr. S 710).</Char></Linea></Exitus></PunktTekst><PunktTekst><Exitus><Linea><Char>2) Til sundhedsministeren af:</Char></Linea></Exitus><Exitus><Linea><Char>Astrid Krag</Char><Char> (S)</Char></Linea></Exitus><Exitus><Linea><Char>Hvad er ministerens holdning til </Char><Char>CO</Char><Char>2</Char><Char>, at apoteket i Frederiksborg på deres hjemmeside offentligt støtter Abortlinjen, der aktivt modarbejder retten til abort, og hvad vil ministeren gøre for at sikre, at apotekerne fortsat agerer objektivt og uvildigt i forbindelse med rådgivning om sygdom? </Char></Linea></Exitus><Exitus><Linea><Char>(Spm. nr. S 711).</Char></Linea></Exitus></PunktTekst><PunktTekst><Exitus><Linea><Char>3) Til statsministeren af:</Char></Linea></Exitus><Exitus><Linea><Char>US 43</Char></Linea></Exitus><Exitus><Linea><Char>(Spm. nr. US 43).</Char></Linea></Exitus></PunktTekst><PunktTekst><Exitus><Linea><Char>4) Til statsministeren af:</Char></Linea></Exitus><Exitus><Linea><Char>Uffe Elbæk</Char><Char> (ALT)</Char></Linea></Exitus><Exitus><Linea><Char>US 44</Char></Linea></Exitus><Exitus><Linea><Char>(Spm. nr. US 44).</Char></Linea></Exitus></PunktTekst><PunktTekst><Exitus><Linea><Char>5) Til statsministeren af:</Char></Linea></Exitus><Exitus><Linea><Char>Uffe Elbæk</Char><Char> (ALT)</Char></Linea></Exitus><Exitus><Linea><Char>US 45</Char></Linea></Exitus><Exitus><Linea><Char>(Spm. nr. US 45).</Char></Linea></Exitus></PunktTekst></DagsordenPlan><DagsordenPunkt><MetaFTAgendaItem><ItemNo>1</ItemNo><ShortTitle>Spørgetime med statsministeren.</ShortTitle></MetaFTAgendaItem><PunktTekst><PreTekst><Exitus><Linea><Char>Det første punkt på dagsordenen er:</Char></Linea></Exitus></PreTekst><Exitus><Linea><Char>1) Spørgetime med statsministeren.</Char></Linea></Exitus></PunktTekst><Aktivitet><DagsordenUnderpunkt><MetaFTAgendaSubItem><SubItemNo>1</SubItemNo><FTCase /><FTCaseNumber>43</FTCaseNumber><FTCaseType>US</FTCaseType><FTCaseStage /><ShortTitle>Spm. nr. US 43</ShortTitle></MetaFTAgendaSubItem><PunktTekst><Exitus><Linea><Char>Spm. nr. US 43</Char></Linea></Exitus><Exitus><Linea><Char>1) Til statsministeren af:</Char></Linea></Exitus><Exitus><Linea><Char>US 43</Char></Linea></Exitus></PunktTekst><Tale><Taler><MetaSpeakerMP><OratorFirstName>Kristian Pihl</OratorFirstName><OratorLastName>Lorentzen</OratorLastName><GroupNameShort>V</GroupNameShort><OratorRole>formand</OratorRole></MetaSpeakerMP><TalerTitel><Linea><Char>Anden næstformand</Char><Char> (Kristian Pihl Lorentzen)</Char></Linea></TalerTitel></Taler><TaleSegment><MetaSpeechSegment><LastModified>2017-10-07T14:46:53</LastModified><EdixiStatus>Available</EdixiStatus><StartDateTime>2017-10-07T14:46:52</StartDateTime><EndDateTime>2017-10-07T14:47:01</EndDateTime></MetaSpeechSegment><TekstGruppe><Exitus><Linea><Char>(Talen er under udarbejdelse)</Char></Linea></Exitus></TekstGruppe></TaleSegment></Tale><Tale><Taler><MetaSpeakerMP><OratorFirstName>Andreas</OratorFirstName><OratorLastName>Steenberg</OratorLastName><GroupNameShort>RV</GroupNameShort><OratorRole>medlem</OratorRole></MetaSpeakerMP><TalerTitel><Linea><Char>Andreas Steenberg</Char><Char> (RV)</Char></Linea></TalerTitel></Taler><TaleSegment><MetaSpeechSegment><LastModified>2017-10-07T14:47:03</LastModified><EdixiStatus>Available</EdixiStatus><StartDateTime>2017-10-07T14:47:01</StartDateTime><EndDateTime>2017-10-07T14:47:18</EndDateTime></MetaSpeechSegment><TekstGruppe><Exitus><Linea><Char>(Talen er under udarbejdelse)</Char></Linea></Exitus></TekstGruppe></TaleSegment></Tale><Tale><Taler><MetaSpeakerMP><OratorFirstName>MødeSlut</OratorFirstName><OratorLastName>MødeSlut</OratorLastName><GroupNameShort>MødeSlut</GroupNameShort><OratorRole>MødeSlut</OratorRole></MetaSpeakerMP><TalerTitel><Linea><Char /><Char /></Linea></TalerTitel></Taler><TaleSegment><MetaSpeechSegment><LastModified>2017-10-07T14:47:18</LastModified><EdixiStatus>Typeset</EdixiStatus><StartDateTime>2017-10-07T14:47:18</StartDateTime></MetaSpeechSegment><TekstGruppe><Exitus><Linea><Char>Mødet er hævet.</Char></Linea><Linea><Char>(Kl.</Char></Linea><Linea><Char>14:47).</Char></Linea></Exitus></TekstGruppe></TaleSegment></Tale></DagsordenUnderpunkt></Aktivitet></DagsordenPunkt></Dokument>