{
    "period": 30,
    "resume": "",
    "sagid": 9904,
    "sponsors": [
        {
            "actor_id": 39,
            "administration": false,
            "name": "Christian Juhl",
            "party": "Enhedslisten"
        },
        {
            "actor_id": 158,
            "administration": false,
            "name": "Eigil Andersen",
            "party": "Socialistisk Folkeparti"
        },
        {
            "actor_id": 184,
            "administration": false,
            "name": "Lennart Damsbo-Andersen",
            "party": "Socialdemokratiet"
        },
        {
            "actor_id": 185,
            "administration": false,
            "name": "Nadeem Farooq",
            "party": "Radikale Venstre"
        },
        {
            "actor_id": 297,
            "administration": false,
            "name": "Maja Panduro",
            "party": "Socialdemokratiet"
        },
        {
            "actor_id": 86,
            "administration": false,
            "name": "Marlene Borst Hansen",
            "party": "Radikale Venstre"
        },
        {
            "actor_id": 85,
            "administration": false,
            "name": "Özlem Sara Cekic",
            "party": "Socialistisk Folkeparti"
        }
    ],
    "statusid": 17,
    "title": "Folketinget konstaterer:\n\n- at regeringen (Socialdemokraterne, Radikale Venstre og Socialistisk Folkeparti) arbejder på at skabe nye arbejdspladser og uddannelsespladser, og at det danske arbejdsmarkedssystem baseres på ret og pligt,\n- at regeringen lægger op til en kontanthjælpsreform, så flere kontanthjælpsmodtagere kommer i uddannelse eller arbejde, og der gøres en særlig indsats for at etablere muligheder for unge ledige,\n- at regeringen ligeledes lægger op til en reform af skattesystemet, og\n- at regeringen således vil fremme en udvikling, hvor flere kommer i uddannelse eller arbejde samtidig med, at regeringen ikke vil acceptere, at socialt udsatte lades i stikken og fastholdes i fattigdom i årevis.",
    "type": 9,
    "vote_id": 1044
}