{
    "area": "Skatteministeriet",
    "period": 30,
    "resume": "Loven indeholder følgende elementer: \n-Aktionærlån beskattes ved optagelsen af lånet, så eksisterende skattemæssige incitamenter til optagelse af aktionærlån som skattefrit alternativ til at hæve løn eller udbytte i selskaber fjernes. \n-Forskudsprocessen ændres med henblik på at sikre en mere korrekt forskudsskat fra borgerne bl.a. ved løbende, automatiske ændringer af forskudsopgørelsen ved indberetninger om renteændringer fra den finansielle sektor. \n\nDer henvises endvidere til omtalen under L 199 og L 199 B.\n",
    "sagid": 12570,
    "sponsors": [
        {
            "actor_id": 1505,
            "administration": true,
            "name": "Thor Möger Pedersen",
            "party": "Not Applicable"
        }
    ],
    "statusid": 11,
    "title": "Forslag til lov om ændring af ligningsloven, kursgevinstloven, skattekontrolloven og kildeskatteloven. (Beskatning af aktionærlån, fortryk og låsning af udvalgte indberetningspligter, bedre forskudsproces m.v.).",
    "type": 3,
    "vote_id": 1323
}