{
    "area": "Økonomi- og Erhvervsministeriet",
    "period": 28,
    "resume": "Loven implementerer EU-direktiv 2009/109/EF i selskabsloven. \nLoven har til formål at gøre det lettere for kapitalselskaber at fusionere og spalte. Desuden indeholder loven en række præciseringer af selskabsloven. \nLoven forventes at medføre administrative lettelser for virksomhederne på op til ca. 5 mio. kr. årligt. \nVed ændringsforslag fra økonomi- og erhvervsministeren udgik bestemmelserne i lovforslaget om, at Erhvervs- og Selskabsstyrelsen skulle kunne fastsætte nærmere regler om offentliggørelse af fusions- og spaltningsplaner m.v. samt bestemmelserne om mulighed for ledelsen for fravalg af underretning om væsentlige begivenheder.",
    "sagid": 14091,
    "sponsors": [
        {
            "actor_id": 83,
            "administration": true,
            "name": "Brian Mikkelsen",
            "party": "Det Konservative Folkeparti"
        }
    ],
    "statusid": 11,
    "title": "Forslag til lov om ændring af lov om aktie- og anpartsselskaber (selskabsloven). (Gennemførelse af ændringsdirektivet om rapporterings- og dokumentationskrav i forbindelse med fusioner og spaltninger m.v.).",
    "type": 3,
    "vote_id": 1469
}