{
    "area": "Udenrigsministeriet",
    "period": 28,
    "resume": "Med folketingsbeslutningen gav Folketinget samtykke til, at regeringen på Danmarks vegne tiltræder en stabiliserings- og associeringsaftale mellem EU og Serbien.\n\nStabiliserings- og associeringsaftalen skal styrke og udvide de politiske og økonomiske forbindelser mellem EU og Serbien. Formålet er også at styrke demokratiet og retsstaten i Serbien og bidrage til politisk, økonomisk og institutionel stabilitet. Desuden skal aftalen gradvis oprette et frihandelsområde mellem EU og Serbien.",
    "sagid": 14550,
    "sponsors": [
        {
            "actor_id": 131,
            "administration": true,
            "name": "Lene Espersen",
            "party": "Det Konservative Folkeparti"
        }
    ],
    "statusid": 10,
    "title": "Forslag til folketingsbeslutning om tiltrædelse af Stabiliserings- og Associeringsaftale mellem De Europæiske Fællesskaber og deres medlemsstater på den ene side og Serbien på den anden side.",
    "type": 5,
    "vote_id": 1543
}