{
    "area": "Ministeriet for Videnskab, Teknologi og Udvikling",
    "period": 28,
    "resume": "På baggrund af en evaluering af universitetsloven fra 2003 udarbejdedes et lovudkast, der blev sendt i en tredelt høring. Loven fremmer internationaliseringen, herunder samarbejde med udenlandske universiteter, og giver det enkelte universitet lidt større frihed til at indrette sin ledelsesstruktur og dermed større muligheder for selv at styre og foretage strategiske valg. Der er dog fortsat en enstrenget ledelsesstruktur. Et ændringsforslag sikrede, at universiteterne ikke kunne pålægges pligtige mål eller konkrete mål, men at ministeren kan \"fastsætte mål\" i udviklingskontrakterne. Loven muliggør også en fusion mellem Aarhus Universitet og Ingeniørhøjskolen i Århus. ",
    "sagid": 14823,
    "sponsors": [
        {
            "actor_id": 1946,
            "administration": true,
            "name": "Charlotte Sahl-Madsen",
            "party": "Not Applicable"
        }
    ],
    "statusid": 11,
    "title": "Forslag til lov om ændring af universitetsloven, lov om teknologioverførsel m.v. ved offentlige\nforskningsinstitutioner og lov om almene boliger m.v. (Opfølgning på evaluering af universitetsloven, internationale uddannelsessamarbejder og selskabsdannelse ved udbud af uddannelse i udlandet m.v.). ",
    "type": 3,
    "vote_id": 1649
}