{
    "area": "Udenrigsministeriet",
    "period": 27,
    "resume": "Med folketingsbeslutningen giver Folketinget sit samtykke til, at et dansk militært bidrag indsættes i NATO's Operation Ocean Shield som led i den internationale indsats mod pirateri ud for Afrikas Horn. Det danske bidrag ventes at skulle deltage i perioderne ultimo januar til medio marts 2010 og igen fra juli/august til november/december 2010.\nBidraget vil bestå af op til 180 personer. Primært et støtteskib af ABSALON-klassen inkl. helikopter og maritim indsatsenhed (militærpoliti, mineryddere og maritime specialstyrker) og et bidrag til operationens ledelse i form af en styrkechef og en stab med ca. 12 danske og seks internationale officerer stillet til rådighed af forskellige NATO-lande.",
    "sagid": 17486,
    "sponsors": [
        {
            "actor_id": 153,
            "administration": true,
            "name": "Per Stig Møller",
            "party": "Det Konservative Folkeparti"
        }
    ],
    "statusid": 10,
    "title": "Forslag til folketingsbeslutning om dansk militært bidrag til NATO’s Operation Ocean Shield som led i den internationale indsats mod pirateri ud for Afrikas Horn.",
    "type": 5,
    "vote_id": 1949
}