{
    "area": "Skatteministeriet",
    "period": 144,
    "resume": "Lovforslaget gennemfører en del af regeringens aftale med Dansk Folkeparti, Liberal Alliance og Det Konservative Folkeparti om at lempe elafgiften for forlystelser i bl.a. forlystelsesparker. Ved ændringen opnås en lempelse i elafgiften for forlystelser på godt 90 øre pr. kWh i 2017. \n",
    "sagid": 70964,
    "sponsors": [
        {
            "actor_id": 24,
            "administration": true,
            "name": "Karsten Lauritzen",
            "party": "Venstre"
        }
    ],
    "statusid": 11,
    "title": "Forslag til lov om ændring af lov om afgift af elektricitet. (Lempelse af elafgift for forlystelser).",
    "type": 3,
    "vote_id": 3272
}