{
    "area": "Social- og Indenrigsministeriet",
    "period": 144,
    "resume": "Formålet med lovforslaget er at skabe mulighed for at sætte den ændring af adoptionsloven, der vedrører et nyt adoptionssystem for international adoptionsformidling, i kraft for Færøerne. Lovforslaget sættes i kraft for Færøerne efter anmodning fra landsstyreområdet for sundheds- og indenlandsanliggender på Færøerne. \n\nLovforslaget kan sættes i kraft for Færøerne ved kongelig anordning. Ikraftsættelsen af lovforslaget for Færøerne forudsætter imidlertid, at myndighedsstrukturen for Færøerne på adoptionsområdet opdateres, så den svarer til strukturen i Danmark i relation til behandlingen af klager over adoptionsafgørelser og tilsyn med adoptionsformidlende organisationer. \n\nDenne opdatering af myndighedsstrukturen på Færøerne forudsætter bl.a., at en generel klagebestemmelse i en tidligere lov om ændring af adoptionsloven sættes i kraft for Færøerne, og at bestemmelsen i adoptionsanordningen for Færøerne om klage over afslag på godkendelse som adoptant ændres. Dette kan kun gennemføres, ved at social- og indenrigsministeren bemyndiges til ved kongelig anordning at sætte den pågældende klagebestemmelse i kraft for Færøerne og til at ændre bestemmelsen i adoptionsanordningen om klage over afslag på godkendelse som adoptant.",
    "sagid": 70714,
    "sponsors": [
        {
            "actor_id": 72,
            "administration": true,
            "name": "Karen Ellemann",
            "party": "Venstre"
        }
    ],
    "statusid": 11,
    "title": "Forslag til lov om ændring af lov om ændring af adoptionsloven og lov om ændring af lov om ægteskabs indgåelse og opløsning og forskellige andre love. (Ikraftsættelse for Færøerne af visse bestemmelser i adoptionsloven).",
    "type": 3,
    "vote_id": 3316
}