{
    "period": 144,
    "resume": "",
    "sagid": 72192,
    "sponsors": [
        {
            "actor_id": 162,
            "administration": false,
            "name": "Karina Adsbøl",
            "party": "Uden for folketingsgrupperne"
        },
        {
            "actor_id": 280,
            "administration": false,
            "name": "Karen J. Klint",
            "party": "Socialdemokratiet"
        },
        {
            "actor_id": 15765,
            "administration": false,
            "name": "Carl Holst",
            "party": "Venstre"
        },
        {
            "actor_id": 69,
            "administration": false,
            "name": "Pernille Skipper",
            "party": "Enhedslisten"
        },
        {
            "actor_id": 15800,
            "administration": false,
            "name": "Henrik Dahl",
            "party": "Liberal Alliance"
        },
        {
            "actor_id": 15768,
            "administration": false,
            "name": "Pernille Schnoor",
            "party": "Alternativet"
        },
        {
            "actor_id": 55,
            "administration": false,
            "name": "Marianne Jelved",
            "party": "Radikale Venstre"
        },
        {
            "actor_id": 15794,
            "administration": false,
            "name": "Trine Torp",
            "party": "Socialistisk Folkeparti"
        },
        {
            "actor_id": 17140,
            "administration": false,
            "name": "Orla Østerby",
            "party": "Uden for folketingsgrupperne"
        }
    ],
    "statusid": 17,
    "title": "Folketinget understreger, at diskrimination af enhver form er uacceptabelt, uanset om det sker på baggrund af køn, seksuel orientering, etnicitet, religion eller handicap.\nDet er folketingets klare intention, at personer med handicap skal beskyttes mod diskrimination også uden for arbejdsmarkedet. \nFolketinget noterer derfor med tilfredshed, at regeringen vil igangsætte et arbejde med at udarbejde et lovforslag om indførelse af et generelt forbud mod diskrimination af mennesker med handicap, der gælder uden for arbejdsmarkedet. Modellen vil indebære klageadgang til Ligebehandlingsnævnet. \nFolketinget konstaterer endvidere, at regler for tilgængelighed, der vedrører nybyggeri, skal overholdes.\nFolketinget støtter, at lovgivningsarbejdet igangsættes hurtigst muligt, således at lovforslaget kan fremsættes i folketingssamlingen 2017-18.",
    "type": 9,
    "vote_id": 3421
}