{
    "period": 146,
    "resume": "",
    "sagid": 75189,
    "sponsors": [
        {
            "actor_id": 79,
            "administration": false,
            "name": "Christian Langballe",
            "party": "Dansk Folkeparti"
        }
    ],
    "statusid": 35,
    "title": "Folketinget konstaterer, at der har været en så massiv tilstrømning af flygtninge og indvandrere til Danmark gennem årene, at det nu og på længere sigt er en alvorlig trussel mod Danmark som nationalstat og mod den folkelige sammenhængskraft. \n\nFolketinget fastslår, at der er brug for et nybrud i dansk udlændingepolitik. Skønt tilstrømningen af flygtninge er gået ned, er det stadig nødvendigt, at landets grænser bevogtes yderligere i forhold til utilsigtet indvandring og tilstrømning af flygtninge, og at Folketing og regering påbegynder en konsekvent hjemsendelse af flygtninge. \n\nFolketinget konstaterer, at en flygtning, som har nydt beskyttelse i Danmark fra krig og ufred, selvfølgelig skal hjem til sit eget land og hjælpe med opbygningen der, når det er muligt. Der er en klar sammenhæng mellem det forhold, at bl.a. syriske flygtninge fra lejre i nærområderne begynder at vende hjem, og det forhold, at syriske flygtninge i Danmark således også skal vende hjem.",
    "type": 9,
    "vote_id": 3915
}