{
    "area": "Justitsministeriet",
    "period": 26,
    "resume": "Beslutningsforslaget pålagde regeringen i 2009 at fremsætte et lovforslag, der indebar, at politiet fik mulighed for at tillade overvågning i særlig udsatte boligområder, og at etablere en finansieringsordning for boligområder, der ikke havde økonomiske ressourcer til indkøb af udstyr.",
    "sagid": 58871,
    "sponsors": [
        {
            "actor_id": 47,
            "administration": false,
            "name": "Karen Hækkerup",
            "party": "Socialdemokratiet"
        },
        {
            "actor_id": 1455,
            "administration": false,
            "name": "René Skau Björnsson",
            "party": "Socialdemokratiet"
        },
        {
            "actor_id": 201,
            "administration": false,
            "name": "Thomas Jensen",
            "party": "Socialdemokratiet"
        },
        {
            "actor_id": 257,
            "administration": false,
            "name": "Bjarne Laustsen",
            "party": "Socialdemokratiet"
        },
        {
            "actor_id": 1880,
            "administration": false,
            "name": "Anne-Marie Meldgaard",
            "party": "Socialdemokratiet"
        },
        {
            "actor_id": 224,
            "administration": false,
            "name": "Flemming Møller Mortensen",
            "party": "Socialdemokratiet"
        },
        {
            "actor_id": 1358,
            "administration": false,
            "name": "Julie Rademacher",
            "party": "Socialdemokratiet"
        }
    ],
    "statusid": 3,
    "title": "Forslag til folketingsbeslutning om videoovervågning af boligområder.",
    "type": 5,
    "vote_id": 4323
}