{
    "area": "Kulturministeriet",
    "period": 25,
    "resume": "Lov om fremme af dopingfri idræt udvides til også at omfatte motions- og fitnesscentre, idet regeringen finder, at der er folkesundhedsmæssige perspektiver i at inddrage motionscentre og fitnesscentre under loven, ligesom ønsket om bekæmpelse af ulovlig handel med dopingstoffer fremmes ved en sådan inddragelse, der skal fremme centres samarbejde med Anti Doping Danmark.",
    "sagid": 53926,
    "sponsors": [
        {
            "actor_id": 83,
            "administration": true,
            "name": "Brian Mikkelsen",
            "party": "Det Konservative Folkeparti"
        }
    ],
    "statusid": 11,
    "title": "Forslag til lov om ændring af lov om fremme af dopingfri idræt. (Informationsordning for motions- og fitnesscentre).",
    "type": 3,
    "vote_id": 4592
}