{
    "area": "Kulturministeriet",
    "period": 31,
    "resume": "Loven implementerer et EU-direktiv om forlængelse af beskyttelsestiden for ophavsret og visse beslægtede rettigheder. Loven indebærer for det første en forlængelse af beskyttelsestiden for udøvende kunstneres ret til lydoptagelser af deres fremførelser fra 50 til 70 år. En tilsvarende forlængelse sker for de rettigheder, som fremstilleren af lydoptagelser har til en given lydoptagelse.\n\nFor det andet harmoniseres beregningen af beskyttelsestiden for musikværker med tekst, så beskyttelsestiden for både musikværket og teksten bliver beregnet som 70 år fra dødsåret for den længstlevende enten komponist eller tekstforfatter.\n\nDerudover indeholder loven nogle ledsageforanstaltninger om udøvende kunstneres ret til et årligt supplerende vederlag i den forlængede beskyttelsestid, deres ret til at bringe en aftale om overdragelse af rettigheder til ophør samt nogle overgangsbestemmelser i forhold til eksisterende rettigheder og overdragelsesaftaler.\n\nLoven træder i kraft den 1. juli 2013. Dog fastsætter justitsministeren tidspunktet for ikrafttræden af § 1, nr. 7.",
    "sagid": 1866,
    "sponsors": [
        {
            "actor_id": 55,
            "administration": true,
            "name": "Marianne Jelved",
            "party": "Radikale Venstre"
        }
    ],
    "statusid": 11,
    "title": "Forslag til lov om ændring af lov om ophavsret. (Forlængelse af beskyttelsestiden for udøvende kunstnere og fremstillere af lydoptagelser, ophør af aftale om overdragelse af en udøvende kunstners rettigheder, udøvende kunstneres ret til årligt supplerende vederlag m.v.).",
    "type": 3,
    "vote_id": 486
}