{
    "area": "Økonomi- og Erhvervsministeriet",
    "period": 23,
    "resume": "Loven indeholder en række mindre justeringer, som har til formål at tilvejebringe grundlag for en række nye, skærpede kontroltiltag med henblik på at fremme kvalitetsskibsfart og højne sikkerheden til søs. \nLoven indeholder også regler om arbejdsgiveransvaret i sager om arbejdsmiljø på skibe.",
    "sagid": 46250,
    "sponsors": [
        {
            "actor_id": 1495,
            "administration": true,
            "name": "Bendt Bendtsen",
            "party": "Det Konservative Folkeparti"
        }
    ],
    "statusid": 11,
    "title": "Forslag til lov om ændring af lov om sikkerhed til søs, sømandsloven og søloven. (Begrænsning af virksomheders strafansvar, gensidig anerkendelse af dispachører m.v.).",
    "type": 3,
    "vote_id": 5014
}