{
    "area": "Socialministeriet",
    "period": 23,
    "resume": "Med beslutningsforslaget skulle lejerne sikres en hurtigere og mere sikker indsats og dermed en bedre beskyttelse, så de hurtigt kom væk fra usunde boliger, der var uegnet til beboelse som følge af skimmelsvamp og lign.",
    "sagid": 49640,
    "sponsors": [
        {
            "actor_id": 951,
            "administration": false,
            "name": "Lissa Mathiasen (udpeget af S)",
            "party": "Socialdemokratiet"
        },
        {
            "actor_id": 257,
            "administration": false,
            "name": "Bjarne Laustsen",
            "party": "Socialdemokratiet"
        }
    ],
    "statusid": 3,
    "title": "Forslag til folketingsbeslutning om forbedring af lejeres retsstilling i forbindelse med usunde lejeboliger, f.eks. som følge af skimmelsvamp og lign.",
    "type": 5,
    "vote_id": 5174
}