{
    "area": "Beskæftigelsesministeriet",
    "period": 20,
    "resume": "Loven giver kommunerne mulighed for at tilbyde redskabet virksomhedspraktik til marginaliserede unge mellem 15 og 18 år. Under virksomhedspraktikken kan kommunen udbetale den unge en godtgørelse, som skal fastsættes i samarbejde med de faglige organisationer med udgangspunkt i den mindste overenskomstmæssige timeløn på det pågældende område. \n\nBaggrund:\n\tDet fremgik af lovforslagets bemærkninger, at den foreslåede mulighed for at anvende virksomhedspraktik til marginaliserede unge var inspireret af projektet »Spydspidsen« i Københavns Kommune. Målgruppen for ordningen var unge med massive problemer.",
    "sagid": 28580,
    "sponsors": [
        {
            "actor_id": 270,
            "administration": true,
            "name": "Claus Hjort Frederiksen",
            "party": "Venstre"
        }
    ],
    "statusid": 11,
    "title": "Forslag til lov om ændring af lov om en aktiv beskæftigelsesindsats. (Virksomhedspraktik til særlig udsatte unge under 18 år).",
    "type": 3,
    "vote_id": 5997
}