{
    "area": "Transport-, Bygnings- og Boligministeriet",
    "period": 146,
    "resume": "Forslaget giver kommunen mulighed for at lade beredskaberne træffe afgørelse om visse ulovlige forhold efter byggeloven vedrørende brandsikkerhed. Forslaget præciserer derudover muligheden for årligt at pristalsregulere byggesagsgebyrer. Endelig kan ministeren efter forslaget fastsætte bestemmelser om straf for overtrædelse af byggevareforordningen. \n\nFormålet med forslaget er at styrke sammenhængen mellem brandreguleringen i byggeloven og de kommunale beredskabers virke.\n",
    "sagid": 75669,
    "sponsors": [
        {
            "actor_id": 99,
            "administration": true,
            "name": "Ole Birk Olesen",
            "party": "Liberal Alliance"
        }
    ],
    "statusid": 11,
    "title": "Forslag til lov om ændring af byggeloven. (Henlæggelse af afgørelseskompetencer vedrørende brandmæssige forhold til § 60-selskaber, pristalsregulering af byggesagsgebyr m.v.).",
    "type": 3,
    "vote_id": 6593
}