{
    "area": "Undervisningsministeriet",
    "period": 148,
    "resume": "Lovforslaget indebærer, at det bliver obligatorisk for alle elever at vælge mindst et 2-årigt praktisk/musisk valgfag i 7.-8. klasse. Folkeskoleeleverne skal tilbydes det praktiske/musiske valgfag håndværk og design og kan derudover tilbydes et eller flere af de praktiske/musiske valgfag: billedkunst, madkundskab eller musik. \n\nEleverne skal til prøve i de 2-årige praktiske/musiske valgfag (håndværk og design, billedkunst, musik og madkundskab) efter 8. klasse. \n\nPrøven vil indgå i beregningen af, om eleven har bestået folkeskolens afgangseksamen. Prøven skal også udbydes på prøveafholdende frie grundskoler, efterskoler og ungdomsskoler. \n\nFolkeskoleeleverne i 8. klasse vil få standpunktskarakterer i det praktiske/musiske valgfag.\n\nElever i folkeskolen får ret til at komme i erhvervspraktik i mindst 1 uge i både 8. og 9. klasse.\n\n",
    "sagid": 78246,
    "sponsors": [
        {
            "actor_id": 73,
            "administration": true,
            "name": "Merete Riisager",
            "party": "Liberal Alliance"
        }
    ],
    "statusid": 11,
    "title": "Forslag til lov om ændring af lov om folkeskolen, lov om friskoler og private grundskoler m.v., lov om efterskoler og frie fagskoler og lov om ungdomsskoler. (Styrket praksisfaglighed m.v.).",
    "type": 3,
    "vote_id": 6976
}