{
    "area": "Erhvervsministeriet",
    "period": 151,
    "resume": "Lovforslaget skal sikre, at udbudsloven er i fuld overensstemmelse med udbudsdirektivet. Med forslaget gennemføres primært lovtekniske ændringer og præciseringer af udbudsloven. \n\nDet indebærer bl.a., at ikkestatslige ordregivere - såsom kommuner og regioner - efter aftale med alle de virksomheder, som opfordres til at afgive tilbud, kan fastsætte kortere tilbudsfrister end lovens normale minimumsfrister.\n\nDet præciseres også i lovforslaget, at virksomheder, der har indgået en bindende aftale om tilbagebetaling af skyldige skatter eller afgifter, ikke kan udelukkes fra deltagelse i konkurrencer om offentlige kontrakter.\n\nHerudover indebærer lovforslaget, at en virksomhed, der ved endelig dom er udelukket fra deltagelse i konkurrencer om offentlige kontrakter, ikke har mulighed for at dokumentere sin pålidelighed.\n\nLoven skal træde i kraft den 1. januar 2020.\n",
    "sagid": 80335,
    "sponsors": [
        {
            "actor_id": 208,
            "administration": true,
            "name": "Simon Kollerup",
            "party": "Socialdemokratiet"
        }
    ],
    "statusid": 11,
    "title": "Forslag til lov om ændring af udbudsloven. (Bortfald af retten til at dokumentere sin pålidelighed, hvis ansøger eller tilbudsgiver er udelukket som følge af endelig dom, præcisering af kravene til indholdet af opfordringer til at afgive tilbud m.v.).",
    "type": 3,
    "vote_id": 7201
}