{
    "area": "Finansministeriet",
    "period": 151,
    "resume": "Lovforslaget ændrer de konkrete niveauer for udgiftslofter for stat, kommuner og regioner for finansårene 2020, 2021 og 2022. Det fremgår af den skriftlige fremsættelse, at ændringerne skal ses i lyset af regeringsskiftet, og at de afspejler regeringens prioriteringer på forslaget til finanslov for 2020, som blev fremsat den 2. oktober 2019.",
    "sagid": 80322,
    "sponsors": [
        {
            "actor_id": 12,
            "administration": true,
            "name": "Nicolai Wammen",
            "party": "Socialdemokratiet"
        }
    ],
    "statusid": 11,
    "title": "Forslag til lov om ændring af lov om fastsættelse af udgiftslofter for stat, kommuner og regioner for finansåret 2020, lov om fastsættelse af udgiftslofter for stat, kommuner og regioner for finansåret 2021 og lov om fastsættelse af udgiftslofter for stat, kommuner og regioner for finansåret 2022. (Konsekvenser af regeringens forslag til finanslov for 2020).",
    "type": 3,
    "vote_id": 7317
}