{
    "area": "Social- og Indenrigsministeriet",
    "period": 151,
    "resume": "Lovforslaget fremsættes i forlængelse af aftalen af 19. marts 2020 mellem regeringen og alle Folketingets partier om en række covid-19-initiativer vedrørende indkøb på det statslige område. Folketingets Finansudvalg har ved tiltrædelse af aktstykke 114 den 23. marts 2020 givet sin tilslutning til, at der til og med 31. oktober 2020 kan dispenseres fra en række bevillingsregler, der har betydning for indkøb i staten. Dispensationerne vil give mulighed for at forudbetale leverancer frem til 1. juli 2020 med en værdi på højst 1 mio. kr. og at undlade at gøre misligholdelsesbestemmelser (f.eks. krav om betaling af bod for forsinkelse) gældende over for leverandører til staten, hvis misligholdelsen kan henføres til covid-19. \nFormålet med lovforslaget er at skabe grundlag for, at kommuner og regioner kan få de samme beføjelser og pligter på indkøbsområdet i forbindelse med covid-19, som statens institutioner har fået. \nMed lovforslaget får social- og indenrigsministeren bemyndigelse til efter forhandling med finansministeren at fastsætte regler om kommuners og regioners indkøb med henblik på at give kommuner og regioner samme beføjelser og pligter i forbindelse med håndteringen af covid-19 som statsinstitutioner og andre institutioner, der er omfattet af de statslige bevillings- og regnskabsregler. \nReglerne vil først blive sat i kraft, når regeringen har fået en tilbagemelding fra Europa-Kommissionen om, at ordningen kan godkendes. \n",
    "sagid": 82559,
    "sponsors": [
        {
            "actor_id": 38,
            "administration": true,
            "name": "Astrid Krag",
            "party": "Socialdemokratiet"
        }
    ],
    "statusid": 11,
    "title": "Forslag til lov om kommuners og regioners indkøb i forbindelse med håndtering af covid-19.\n\n",
    "type": 3,
    "vote_id": 7434
}