{
    "area": "Uddannelses- og Forskningsministeriet",
    "period": 153,
    "resume": "Lovforslaget er en konsekvens af aftale den 2. marts 2020 mellem regeringen (Socialdemokratiet), Venstre, Dansk Folkeparti, Radikale Venstre, Socialistisk Folkeparti, Det Konservative Folkeparti og Liberal Alliance om at afsætte 5 mio. kr. årligt til Studievalg Danmarks vejledningsindsats om erhvervs-uddannelserne. \n\nFormålet med lovforslaget er således at udvide Studievalg Danmarks vejledningsområde, så vejledningen fremover også omfatter valg af erhvervsuddannelse. Samfundet har brug for, at flere unge får valgt den rette uddannelse, og at de vejledes om alle de muligheder, de har. Det gælder eksempelvis også de elever, der starter på gymnasiet, men som efterfølgende overvejer at begynde på en erhvervsuddannelse.\n\nLovforslaget foreslås at træde i kraft den 1. januar 2021.",
    "sagid": 84963,
    "sponsors": [
        {
            "actor_id": 286,
            "administration": true,
            "name": "Ane Halsboe-Jørgensen",
            "party": "Socialdemokratiet"
        }
    ],
    "statusid": 11,
    "title": "Forslag til lov om ændring af lov om Studievalg Danmark. (Udvidelse af Studievalg Danmarks vejledningsområde).",
    "type": 3,
    "vote_id": 7509
}