{
    "area": "Social- og Ældreministeriet",
    "period": 153,
    "resume": "Formålet med forslaget er at sikre ret til ambulant behandling for voksne og deres eventuelle medfølgende børn, som har været udsat for vold, trusler om vold eller en tilsvarende krise i relation til familie- eller samlivsforhold. Ifølge forslagsstillerne skal behandlingstilbuddene til voldsudsatte rumme voksne og børn af alle køn og i alle landsdele. Den tilsynsførende myndighed skal derfor sikre, at kapaciteten i tilbuddene modsvarer efterspørgslen i forhold til geografi og målgrupper, herunder tage hensyn til, at kvinder langt oftere end mænd er udsat for grov partnervold og den geografiske overrepræsentation i hovedstadsområdet. Forslagsstillerne mener, at retten til ambulant behandling skal skrives ind i serviceloven som en selvstændig paragraf. Beslutningsforslaget er en opdateret genfremsættelse af beslutningsforslag nr. B 121, folketingsåret 2019-20. ",
    "sagid": 86817,
    "sponsors": [
        {
            "actor_id": 18691,
            "administration": false,
            "name": "Sikandar Siddique",
            "party": "Uden for folketingsgrupperne"
        },
        {
            "actor_id": 225,
            "administration": false,
            "name": "Uffe Elbæk",
            "party": "Frie Grønne"
        },
        {
            "actor_id": 18692,
            "administration": false,
            "name": "Susanne Zimmer",
            "party": "Uden for folketingsgrupperne"
        }
    ],
    "statusid": 16,
    "title": "Forslag til folketingsbeslutning om ret til ambulant behandling for voldsudsatte og deres børn.",
    "type": 5,
    "vote_id": 8106
}