{
    "area": "Erhvervsministeriet",
    "period": 155,
    "resume": "Formålet med lovforslaget er at tilrette lovgivningen i lyset af ændringerne i Rådets Forordning (EF) nr. 428/2009 om eksportkontrol af produkter med dobbelt anvendelse (dualuseforordningen). Den nye forordning trådte i kraft den 9. september 2021. Lovforslaget indfører bl.a. en straffebestemmelse for overtrædelse af den nye kontrol med cyberovervågningsprodukter.",
    "sagid": 89645,
    "sponsors": [
        {
            "actor_id": 208,
            "administration": true,
            "name": "Simon Kollerup",
            "party": "Socialdemokratiet"
        }
    ],
    "statusid": 11,
    "title": "Forslag til lov om ændring af lov om anvendelsen af visse af Den Europæiske Unions retsakter om økonomiske forbindelser til tredjelande m.v. (Ophævelse af forbud mod teknisk bistand og indførelse af straffebestemmelse for ny kontrol med cyberovervågningsprodukter).",
    "type": 3,
    "vote_id": 8416
}