{
    "area": "Transportministeriet",
    "period": 155,
    "resume": "Med lovforslaget ændres sprogkravet ved optagelse på chaufførkurset, og afgiften for udstedelse af en tilladelse til erhvervsmæssig persontransport ændres til et gebyr. Desuden indebærer lovforslaget, at overenskomstbestemmelsen i taxilovens § 10 også skal gælde tilladelser udstedt efter den tidligere gældende taxilov. \n\nLovforslaget er en udmøntning af aftale om justering af taxiloven m.v. af 16. marts 2021 mellem regeringen (Socialdemokratiet), Radikale Venstre, Socialistisk Folkeparti, Det Konservative Folkeparti, Venstre og Dansk Folkeparti. \n\nLoven forventes at træde i kraft den 1. januar 2022.",
    "sagid": 89665,
    "sponsors": [
        {
            "actor_id": 120,
            "administration": true,
            "name": "Benny Engelbrecht",
            "party": "Socialdemokratiet"
        }
    ],
    "statusid": 11,
    "title": "Forslag til lov om ændring af taxiloven. (Dokumentationskrav til brug for tilsyn og med hensyn til danskkundskaber for chauffører, gebyrer og overenskomstkrav for tilladelser i henhold til tidligere gældende lov om taxikørsel m.v.).",
    "type": 3,
    "vote_id": 8423
}