{
    "area": "Erhvervsministeriet",
    "period": 155,
    "resume": "Lovforslaget skal sikre, at Kommissionens gennemførelsesforordning (EU) 2018/1212 af 3. september 2018 om fastsættelse af minimumskrav vedrørende gennemførelsen af bestemmelserne i Europa-Parlamentets og Rådets direktiv 2007/36/EF for så vidt angår identifikation af aktionærer, videregivelse af oplysninger og lettelse af udøvelsen af aktionærrettigheder samt senere ændringer af forordningen kan gennemføres i Grønland.\n\nForordningen har fundet anvendelse i EU- / EØS-medlemsstater fra den 3. september 2020, men da Grønland ikke er medlem af EU, kan bestemmelser svarende til gennemførelsesforordningen for Grønlands vedkommende kun gennemføres ved dansk lov.",
    "sagid": 89965,
    "sponsors": [
        {
            "actor_id": 208,
            "administration": true,
            "name": "Simon Kollerup",
            "party": "Socialdemokratiet"
        }
    ],
    "statusid": 11,
    "title": "Forslag til lov for Grønland om identifikation af aktionærer, videregivelse af oplysninger og lettelse af udøvelsen af aktionærrettigheder.",
    "type": 3,
    "vote_id": 8463
}