{
    "area": "Skatteministeriet",
    "period": 155,
    "resume": "",
    "sagid": 90774,
    "sponsors": [
        {
            "actor_id": 220,
            "administration": true,
            "name": "Morten Bødskov",
            "party": "Socialdemokratiet"
        }
    ],
    "statusid": 11,
    "title": "Forslag til lov om ændring af lov om forskellige forbrugsafgifter, momsloven og forskellige andre love og ophævelse af lov om ændring af lov om forskellige forbrugsafgifter og opkrævningsloven. (Indførelse af afgift på nikotinprodukter, sammenlægning af afgiftssatserne for røgfri tobak, justering af betingelser for fjernsalgsregistrering for visse punktafgifter, ændring af momsloven som reaktion på covid-19-pandemien m.v.).",
    "type": 3,
    "vote_id": 8495
}